Workbook

Sheet Tổng quan
A1: KẾ HOẠCH TRIỂN KHAI API TÍCH HỢP RDM ↔ SAP ECC 6.0 – 40 NGÀY
A2: Nguồn: Tafico_RDM-SAP_API_Business_Scope_v1.1 – sheet "Phạm vi - Scope" (24 đối tượng: 21 API + 3 Z-Report). Phiên bản kế hoạch v1.0 – lập ngày 28/10/2026
A4: Thời gian | B4: 29/10/2026 → 07/12/2026 (40 ngày lịch = 28 ngày làm việc T2–T6 + 6 thứ Bảy dự phòng/OT cho Tuấn & Nam)
A5: Kiến trúc | B5: REST API (ASP.NET Core .NET 8) – xác thực JWT (role + phạm vi dữ liệu theo đối tác) – SAP NCo 3.1 – SQL Server (ghi qua stored procedure) – Hangfire job nền
A6: Logging | B6: Phía API: Serilog + Correlation-Id + rdm.SapCallLog. Phía SAP (bổ sung): bảng ZRDM_API_LOG/ZRDM_API_LOGI + Application Log SLG1 (object ZRDM) + report ZRDM_LOG_VIEW; Correlation-Id truyền từ API xuống mọi FM
A7: Nguyên tắc API | B7: Mỗi đối tượng × hành động = 1 API riêng (không gộp API tổng). Tổng 112 API – xem sheet "Danh mục API"
A8: Test & tài liệu | B8: Unit test (xUnit), integration DEV930, test theo nhóm A/B/C/D, SIT, hiệu năng, bảo mật, UAT. Tài liệu: BRD/mapping, SAD, API guide, TS ABAP, FS báo cáo, user guide, runbook
A9: Phân bổ chủ đạo | B9: Tuấn + Nam ≈ 68–70% công (API, ABAP FM, logging); Khang: 3 báo cáo Z (014, 017, 023) + RFC đọc kết quả báo cáo; Hằng: tư vấn spec giá & khuyến mại (SD); Sơn: tư vấn spec 3 báo cáo + bút toán FI
A10: Chi phí | B10: Ngân sách 195 triệu VNĐ: Nam 140 · Khang 30 · Hằng 15 · Sơn 10 – Tuấn không tính phí. Phân tích đóng góp của Tuấn và chi phí nếu không có Tuấn: sheet "Chi phí & Đóng góp Tuấn"
A12: PHÂN BỔ NGUỒN LỰC
A13: Thành viên | B13: Vai trò | C13: Công (ngày) | D13: Tỷ trọng | E13: Năng lực T2–T6 | F13: % sử dụng | G13: Trách nhiệm chính
A14: Tuấn | B14: SA / ABAP / BA | C14: =SUM('WBS chi tiết'!H5:H166) | D14: =C14/C$19 | E14: 28 | F14: =C14/E14 | G14: SA/BA: kiến trúc, JWT, logging API, mapping, ~95 API .NET, unit/SIT/UAT, tài liệu API & vận hành
A15: Nam | B15: ABAP / Techlead | C15: =SUM('WBS chi tiết'!I5:I166) | D15: =C15/C$19 | E15: 28 | F15: =C15/E15 | G15: Techlead ABAP: logging SAP, FM RFC (giá, HĐ, free-bag, sản lượng, credit memo, khung FI), API hạch toán 016/019/020, transport, review code
A16: Khang | B16: ABAP | C16: =SUM('WBS chi tiết'!J5:J166) | D16: =C16/C$19 | E16: 28 | F16: =C16/E16 | G16: 3 Z-Report (EPD, lãi quá hạn, đối chiếu công nợ) + RFC đọc kết quả 015/018, TS báo cáo
A17: Sơn | B17: FICO consultant | C17: =SUM('WBS chi tiết'!K5:K166) | D17: =C17/C$19 | E17: 28 | F17: =C17/E17 | G17: Spec 3 báo cáo + ma trận bút toán FI, duyệt test case FI, SIT/UAT FI, user guide FI
A18: Hằng | B18: SD consultant | C18: =SUM('WBS chi tiết'!L5:L166) | D18: =C18/C$19 | E18: 28 | F18: =C18/E18 | G18: Spec giá ZVLP/ZVDI/ZMIN/ZVIV, free-bag, hợp đồng, sản lượng, credit memo; test case & UAT SD
A19: TỔNG | C19: =SUM(C14:C18) | D19: =SUM(D14:D18)
A20: Tỷ trọng Tuấn + Nam | C20: =C14+C15 | D20: =D14+D15
A21: % sử dụng > 100% nghĩa là có làm thêm thứ Bảy (xem sheet "Nguồn lực theo tuần").
A23: MỐC CHÍNH (MILESTONE)
A24: Mốc | B24: Ngày | C24: Nội dung | G24: Điều kiện đạt
A25: M0 – Kickoff | B25: 29/10/2026 | C25: Kickoff, kiểm tra môi trường DEV930 | G25: Môi trường gọi RFC OK
A26: M1 – Chốt yêu cầu | B26: 04/11/2026 | C26: Decision log SD/FI, ma trận bút toán, mapping field ký | G26: BRD + mapping sign-off
A27: M2 – Nền tảng | B27: 06/11/2026 | C27: JWT, logging API, logging SAP (ZRDM_API_LOG + SLG1) | G27: Correlation-Id truy được 2 phía
A28: M3 – Bàn giao nhóm A | B28: 13/11/2026 | C28: ZRDM-001/002/003 – master data (42 API) | G28: Test nhóm A pass
A29: M4 – Bàn giao nhóm B | B29: 20/11/2026 | C29: ZRDM-004…009 – giá, VAT, HĐ, tín dụng, free-bag | G29: Test nhóm B pass
A30: M5 – Bàn giao nhóm C + D (FI) | B30: 27/11/2026 | C30: ZRDM-010…022 – HĐ free-bag, sản lượng, credit memo, FI, báo cáo 014/017 | G30: Test nhóm C/D pass
A31: M6 – Bàn giao 023/024 | B31: 30/11/2026 | C31: Biên bản đối chiếu công nợ (report + API) | G31: Kế toán xác nhận số liệu
A32: M7 – SIT xong | B32: 02/12/2026 | C32: SIT end-to-end + hiệu năng | G32: Không còn lỗi Critical/High
A33: M8 – UAT ký | B33: 04/12/2026 | C33: UAT người dùng Tafico | G33: Biên bản UAT
A34: M9 – Go-live | B34: 07/12/2026 | C34: Transport PRD, deploy, bàn giao tài liệu | G34: Nghiệm thu
A36: GIẢ ĐỊNH & LƯU Ý
A37: • Backend hiện tại đã có khung (JWT, logging API, idempotency, master data, giá BAPI, FB01/FB75/đảo chứng từ, VA01/VA41/VBN1) – API "Có sẵn" chỉ rà soát + test, "Điều chỉnh" sửa theo spec mới, "Mới" code mới.
A38: • Ước lượng theo ngày công (md); lịch được xếp tự động theo năng lực từng người, ưu tiên hạn bàn giao SOW, tôn trọng phụ thuộc ABAP → API.
A39: • Thứ Bảy là ngày dự phòng/OT, chỉ dùng cho Tuấn & Nam khi việc có nguy cơ trễ hạn SOW.
A40: • Một số API nhóm B/D (đánh dấu cam ở WBS) kết thúc vào thứ Bảy ngay sau hạn SOW 1 ngày – cần chốt với Tafico hoặc tăng OT.
A41: • Open point ở sheet "Rủi ro & Open point" phải chốt trước 04/11; chốt muộn sẽ đẩy lùi nhóm B/C/D.
A42: • Nam đảm nhận thêm API .NET cho 3 nghiệp vụ hạch toán FI (016/019/020) vì dùng trực tiếp khung FI Z_RDM_FI_POST do Nam viết.
A43: • ZRDM-008 (bảo lãnh ngân hàng) không triển khai theo SOW v1.1.

Sheet Danh mục API
A1: DANH MỤC API – mỗi đối tượng × hành động = 1 API
A2: 112 API · Trạng thái: Có sẵn = đã có trong backend, rà soát + test · Điều chỉnh = có, sửa theo spec · Mới = xây mới
A4: STT | B4: Mã API | C4: Mã SOW | D4: Nhóm | E4: Đối tượng | F4: Hành động | G4: Method | H4: Endpoint | I4: Hàm SAP / nguồn dữ liệu | J4: Object ABAP phụ thuộc | K4: Trạng thái | L4: Quyền JWT | M4: Idempotency (requestId) | N4: Log API / Log SAP | O4: Người làm | P4: Công (md) | Q4: Bắt đầu | R4: Kết thúc | S4: Hạn SOW | T4: Cảnh báo
A5: 1 | B5: API-001 | C5: Chung | D5: Chung | E5: Xác thực | F5: Cấp token JWT | G5: POST | H5: /api/auth/token | I5: – | J5: – | K5: Điều chỉnh | L5: Partner (ghi) | M5: Bắt buộc | N5: Có / Có | O5: Tuấn | P5: 0.25 | Q5: 46331 | R5: 46331 | S5: –
A6: 2 | B6: API-002 | C6: Chung | D6: Chung | E6: Xác thực | F6: Làm mới token (refresh) | G6: POST | H6: /api/auth/refresh | I6: – | J6: – | K6: Mới | L6: Partner (ghi) | M6: Bắt buộc | N6: Có / Có | O6: Tuấn | P6: 0.25 | Q6: 46331 | R6: 46331 | S6: –
A7: 3 | B7: API-003 | C7: Chung | D7: Chung | E7: Xác thực | F7: Thông tin user hiện tại + phạm vi dữ liệu | G7: GET | H7: /api/auth/me | I7: – | J7: – | K7: Điều chỉnh | L7: Partner (đọc) | M7: – | N7: Có / – | O7: Tuấn | P7: 0.1 | Q7: 46332 | R7: 46332 | S7: –
A8: 4 | B8: API-004 | C8: Chung | D8: Chung | E8: Người dùng | F8: Danh sách user | G8: GET | H8: /api/auth/users | I8: – | J8: – | K8: Có sẵn | L8: Admin | M8: – | N8: Có / – | O8: Tuấn | P8: 0.1 | Q8: 46325 | R8: 46325 | S8: –
A9: 5 | B9: API-005 | C9: Chung | D9: Chung | E9: Người dùng | F9: Tạo/sửa user, role, phạm vi đối tác | G9: PUT | H9: /api/auth/users/{username} | I9: – | J9: – | K9: Điều chỉnh | L9: Admin | M9: Bắt buộc | N9: Có / Có | O9: Tuấn | P9: 0.25 | Q9: 46332 | R9: 46332 | S9: –
A10: 6 | B10: API-006 | C10: Chung | D10: Chung | E10: Chứng từ RDM | F10: Tra cứu theo Id | G10: GET | H10: /api/postings/{id} | I10: – | J10: – | K10: Có sẵn | L10: Partner (đọc) | M10: – | N10: Có / – | O10: Tuấn | P10: 0.1 | Q10: 46325 | R10: 46325 | S10: –
A11: 7 | B11: API-007 | C11: Chung | D11: Chung | E11: Chứng từ RDM | F11: Tra cứu theo requestId | G11: GET | H11: /api/postings/{operation}/{requestId} | I11: – | J11: – | K11: Có sẵn | L11: Partner (đọc) | M11: – | N11: Có / – | O11: Tuấn | P11: 0.1 | Q11: 46325 | R11: 46325 | S11: –
A12: 8 | B12: API-008 | C12: Chung | D12: Chung | E12: Chứng từ RDM | F12: Tìm kiếm danh sách | G12: GET | H12: /api/postings | I12: – | J12: – | K12: Có sẵn | L12: Partner (đọc) | M12: – | N12: Có / – | O12: Tuấn | P12: 0.1 | Q12: 46325 | R12: 46325 | S12: –
A13: 9 | B13: API-009 | C13: Chung | D13: Chung | E13: Kết nối SAP | F13: Kiểm tra kết nối | G13: GET | H13: /api/sap/ping | I13: RFC_PING | J13: – | K13: Có sẵn | L13: Partner (đọc) | M13: – | N13: Có / – | O13: Tuấn | P13: 0.1 | Q13: 46325 | R13: 46325 | S13: –
A14: 10 | B14: API-010 | C14: Chung | D14: Chung | E14: Log API→SAP | F14: Danh sách log gọi SAP | G14: GET | H14: /api/admin/sap-calls | I14: – | J14: – | K14: Có sẵn | L14: Admin | M14: – | N14: Có / – | O14: Tuấn | P14: 0.1 | Q14: 46332 | R14: 46332 | S14: –
A15: 11 | B15: API-011 | C15: Chung | D15: Chung | E15: Log API→SAP | F15: Chi tiết 1 lần gọi | G15: GET | H15: /api/admin/sap-calls/{id} | I15: – | J15: – | K15: Có sẵn | L15: Admin | M15: – | N15: Có / – | O15: Tuấn | P15: 0.1 | Q15: 46332 | R15: 46332 | S15: –
A16: 12 | B16: API-012 | C16: Chung | D16: Chung | E16: Log trên SAP | F16: Danh sách log SAP (ZRDM_API_LOG) | G16: GET | H16: /api/admin/sap-logs | I16: Z_RDM_LOG_READ | J16: L.3 | K16: Mới | L16: Admin | M16: – | N16: Có / Có | O16: Tuấn | P16: 0.25 | Q16: 46339 | R16: 46339 | S16: –
A17: 13 | B17: API-013 | C17: Chung | D17: Chung | E17: Log trên SAP | F17: Log SAP theo Correlation-Id | G17: GET | H17: /api/admin/sap-logs/{correlationId} | I17: Z_RDM_LOG_READ | J17: L.3 | K17: Mới | L17: Admin | M17: – | N17: Có / Có | O17: Tuấn | P17: 0.25 | Q17: 46339 | R17: 46342 | S17: –
A18: 14 | B18: API-014 | C18: ZRDM-001 | D18: A | E18: Sold-to | F18: Đồng bộ từ SAP (full + delta) | G18: POST | H18: /api/master-data/sold-to/sync | I18: RFC_READ_TABLE + Z_RDM_CUST_DELTA_GET | J18: N.001 | K18: Điều chỉnh | L18: Partner (ghi) | M18: Bắt buộc | N18: Có / Có | O18: Tuấn | P18: 0.5 | Q18: 46332 | R18: 46335 | S18: 46339
A19: 15 | B19: API-015 | C19: ZRDM-001 | D19: A | E19: Sold-to | F19: Lấy danh sách (lọc, phân trang, changedSince) | G19: GET | H19: /api/master-data/sold-to | I19: DB local | J19: – | K19: Điều chỉnh | L19: Partner (đọc) | M19: – | N19: Có / – | O19: Tuấn | P19: 0.25 | Q19: 46335 | R19: 46335 | S19: 46339
A20: 16 | B20: API-016 | C20: ZRDM-001 | D20: A | E20: Sold-to | F20: Lấy chi tiết 1 KH | G20: GET | H20: /api/master-data/sold-to/{customer} | I20: DB local | J20: – | K20: Có sẵn | L20: Partner (đọc) | M20: – | N20: Có / – | O20: Tuấn | P20: 0.05 | Q20: 46335 | R20: 46335 | S20: 46339
A21: 17 | B21: API-017 | C21: ZRDM-001 | D21: A | E21: Ship-to | F21: Đồng bộ từ SAP (full + delta) | G21: POST | H21: /api/master-data/ship-to/sync | I21: RFC_READ_TABLE + Z_RDM_CUST_DELTA_GET | J21: N.001 | K21: Điều chỉnh | L21: Partner (ghi) | M21: Bắt buộc | N21: Có / Có | O21: Tuấn | P21: 0.25 | Q21: 46335 | R21: 46335 | S21: 46339
A22: 18 | B22: API-018 | C22: ZRDM-001 | D22: A | E22: Ship-to | F22: Lấy danh sách | G22: GET | H22: /api/master-data/ship-to | I22: DB local | J22: – | K22: Điều chỉnh | L22: Partner (đọc) | M22: – | N22: Có / – | O22: Tuấn | P22: 0.1 | Q22: 46335 | R22: 46335 | S22: 46339
A23: 19 | B23: API-019 | C23: ZRDM-001 | D23: A | E23: Ship-to | F23: Lấy chi tiết 1 ship-to | G23: GET | H23: /api/master-data/ship-to/{customer} | I23: DB local | J23: – | K23: Có sẵn | L23: Partner (đọc) | M23: – | N23: Có / – | O23: Tuấn | P23: 0.05 | Q23: 46335 | R23: 46335 | S23: 46339
A24: 20 | B24: API-020 | C24: ZRDM-001 | D24: A | E24: Quan hệ Sold-to ↔ Ship-to | F24: Đồng bộ từ SAP | G24: POST | H24: /api/master-data/sold-to-ship-to/sync | I24: RFC_READ_TABLE KNVP | J24: – | K24: Có sẵn | L24: Partner (ghi) | M24: Bắt buộc | N24: Có / Có | O24: Tuấn | P24: 0.1 | Q24: 46335 | R24: 46335 | S24: 46339
A25: 21 | B25: API-021 | C25: ZRDM-001 | D25: A | E25: Quan hệ Sold-to ↔ Ship-to | F25: Lấy danh sách | G25: GET | H25: /api/master-data/sold-to-ship-to | I25: DB local | J25: – | K25: Có sẵn | L25: Partner (đọc) | M25: – | N25: Có / – | O25: Tuấn | P25: 0.05 | Q25: 46335 | R25: 46335 | S25: 46339
A26: 22 | B26: API-022 | C26: ZRDM-001 | D26: A | E26: Sales Org | F26: Đồng bộ từ SAP | G26: POST | H26: /api/master-data/sales-orgs/sync | I26: RFC_READ_TABLE TVKO/TVKOT | J26: – | K26: Có sẵn | L26: Partner (ghi) | M26: Bắt buộc | N26: Có / Có | O26: Tuấn | P26: 0.1 | Q26: 46335 | R26: 46335 | S26: 46339
A27: 23 | B27: API-023 | C27: ZRDM-001 | D27: A | E27: Sales Org | F27: Lấy danh sách | G27: GET | H27: /api/master-data/sales-orgs | I27: DB local | J27: – | K27: Có sẵn | L27: Partner (đọc) | M27: – | N27: Có / – | O27: Tuấn | P27: 0.05 | Q27: 46336 | R27: 46336 | S27: 46339
A28: 24 | B28: API-024 | C28: ZRDM-001 | D28: A | E28: Kênh phân phối | F28: Đồng bộ từ SAP | G28: POST | H28: /api/master-data/distribution-channels/sync | I28: RFC_READ_TABLE TVTW/TVTWT | J28: – | K28: Mới | L28: Partner (ghi) | M28: Bắt buộc | N28: Có / Có | O28: Tuấn | P28: 0.25 | Q28: 46336 | R28: 46336 | S28: 46339
A29: 25 | B29: API-025 | C29: ZRDM-001 | D29: A | E29: Kênh phân phối | F29: Lấy danh sách | G29: GET | H29: /api/master-data/distribution-channels | I29: DB local | J29: – | K29: Mới | L29: Partner (đọc) | M29: – | N29: Có / – | O29: Tuấn | P29: 0.25 | Q29: 46336 | R29: 46336 | S29: 46339
... A87: 83 | B87: API-083 | C87: ZRDM-009 | D87: B | E87: Chương trình free-bag | F87: Sửa chương trình | G87: POST | H87: /api/sd/freebag-programs/change | I87: Z_RDM_FREEGOODS_MAINTAIN | J87: N.009 | K87: Mới | L87: Partner (ghi) | M87: Bắt buộc | N87: Có / Có | O87: Tuấn | P87: 0.25 | Q87: 46340 | R87: 46340 | S87: 46346
A88: 84 | B88: API-084 | C88: ZRDM-009 | D88: B | E88: Chương trình free-bag | F88: Hủy hiệu lực chương trình | G88: POST | H88: /api/sd/freebag-programs/invalidate | I88: Z_RDM_FREEGOODS_MAINTAIN | J88: N.009 | K88: Mới | L88: Partner (ghi) | M88: Bắt buộc | N88: Có / Có | O88: Tuấn | P88: 0.25 | Q88: 46346 | R88: 46347 | S88: 46346 | T88: Trễ 1 ngày – OT thứ Bảy
A89: 85 | B89: API-085 | C89: ZRDM-009 | D89: B | E89: Chương trình free-bag | F89: Lấy danh sách / chi tiết chương trình | G89: GET | H89: /api/sd/freebag-programs | I89: Z_RDM_FREEGOODS_GET | J89: N.009b | K89: Mới | L89: Partner (đọc) | M89: – | N89: Có / Có | O89: Tuấn | P89: 0.25 | Q89: 46347 | R89: 46347 | S89: 46346 | T89: Trễ 1 ngày – OT thứ Bảy
A90: 86 | B90: API-086 | C90: ZRDM-010 | D90: C | E90: HĐ free-bag | F90: Tạo HĐ free-bag | G90: POST | H90: /api/sd/freebag-contracts | I90: Z_RDM_FREEBAG_CONTRACT | J90: N.010 | K90: Mới | L90: Partner (ghi) | M90: Bắt buộc | N90: Có / Có | O90: Tuấn | P90: 0.5 | Q90: 46349 | R90: 46349 | S90: 46353
A91: 87 | B91: API-087 | C91: ZRDM-010 | D91: C | E91: HĐ free-bag | F91: Cập nhật HĐ free-bag (khi tồn thay đổi) | G91: POST | H91: /api/sd/freebag-contracts/change | I91: Z_RDM_FREEBAG_CONTRACT | J91: N.010 | K91: Mới | L91: Partner (ghi) | M91: Bắt buộc | N91: Có / Có | O91: Tuấn | P91: 0.25 | Q91: 46349 | R91: 46349 | S91: 46353
A92: 88 | B92: API-088 | C92: ZRDM-010 | D92: C | E92: HĐ free-bag | F92: Lấy chi tiết HĐ free-bag | G92: GET | H92: /api/sd/freebag-contracts/{contractNo} | I92: Z_RDM_CONTRACT_GET | J92: N.006a | K92: Mới | L92: Partner (đọc) | M92: – | N92: Có / Có | O92: Tuấn | P92: 0.25 | Q92: 46349 | R92: 46349 | S92: 46353
A93: 89 | B93: API-089 | C93: ZRDM-011 | D93: C | E93: Sản lượng tính chiết khấu | F93: Lấy sản lượng (phân trang, theo KH/kỳ) | G93: GET | H93: /api/sd/sales-volumes | I93: Z_RDM_SALES_VOLUME_GET | J93: N.011a | K93: Mới | L93: Partner (đọc) | M93: – | N93: Có / Có | O93: Tuấn | P93: 0.5 | Q93: 46350 | R93: 46350 | S93: 46353
A94: 90 | B94: API-090 | C94: ZRDM-011 | D94: C | E94: Sản lượng tính chiết khấu | F94: Trích xuất khối lượng lớn (job nền) | G94: POST | H94: /api/sd/sales-volumes/jobs/export | I94: Z_RDM_SALES_VOLUME_GET | J94: N.011a | K94: Mới | L94: Partner (ghi) | M94: Bắt buộc | N94: Có / Có | O94: Tuấn | P94: 0.25 | Q94: 46350 | R94: 46350 | S94: 46353
A95: 91 | B95: API-091 | C95: ZRDM-011 | D95: C | E95: Free-bag đã chi trả | F95: Lấy dữ liệu free-bag đã chi trả (phân trang) | G95: GET | H95: /api/sd/freebag-payouts | I95: Z_RDM_FREEBAG_PAID_GET | J95: N.011b | K95: Mới | L95: Partner (đọc) | M95: – | N95: Có / Có | O95: Tuấn | P95: 0.25 | Q95: 46351 | R95: 46351 | S95: 46353
A96: 92 | B96: API-092 | C96: ZRDM-012 | D96: C | E96: Credit memo request | F96: Tạo yêu cầu giảm giá / cấn trừ công nợ | G96: POST | H96: /api/sd/credit-memo-requests | I96: Z_RDM_CMR_CREATE | J96: N.012 | K96: Mới | L96: Partner (ghi) | M96: Bắt buộc | N96: Có / Có | O96: Tuấn | P96: 0.5 | Q96: 46352 | R96: 46352 | S96: 46353
A97: 93 | B97: API-093 | C97: ZRDM-012 | D97: C | E97: Credit memo request | F97: Tra cứu trạng thái / chứng từ liên quan | G97: GET | H97: /api/sd/credit-memo-requests/{docNo} | I97: RFC_READ_TABLE VBAK/VBFA | J97: N.012 | K97: Mới | L97: Partner (đọc) | M97: – | N97: Có / – | O97: Tuấn | P97: 0.25 | Q97: 46352 | R97: 46352 | S97: 46353
A98: 94 | B98: API-094 | C98: ZRDM-013 | D98: C | E98: Bút toán CK trực tiếp | F98: Kiểm tra trước khi hạch toán | G98: POST | H98: /api/fi/discount-postings/check | I98: BAPI_ACC_DOCUMENT_CHECK | J98: N.013 | K98: Mới | L98: Partner (ghi) | M98: Bắt buộc | N98: Có / Có | O98: Tuấn | P98: 0.25 | Q98: 46350 | R98: 46350 | S98: 46353
A99: 95 | B99: API-095 | C99: ZRDM-013 | D99: C | E99: Bút toán CK trực tiếp | F99: Hạch toán (gồm quyết toán âm) | G99: POST | H99: /api/fi/discount-postings | I99: Z_RDM_FI_POST | J99: N.013 | K99: Mới | L99: Partner (ghi) | M99: Bắt buộc | N99: Có / Có | O99: Tuấn | P99: 0.5 | Q99: 46351 | R99: 46351 | S99: 46353
A100: 96 | B100: API-096 | C100: ZRDM-015 | D100: D | E100: CK thanh toán trước | F100: Lấy danh sách kết quả tính | G100: GET | H100: /api/fi/early-payment-discounts | I100: Z_RDM_EPD_GET | J100: K.015 | K100: Mới | L100: Partner (đọc) | M100: – | N100: Có / Có | O100: Tuấn | P100: 0.25 | Q100: 46351 | R100: 46351 | S100: 46353
A101: 97 | B101: API-097 | C101: ZRDM-015 | D101: D | E101: CK thanh toán trước | F101: Lấy chi tiết theo KH/kỳ | G101: GET | H101: /api/fi/early-payment-discounts/{customer} | I101: Z_RDM_EPD_GET | J101: K.015 | K101: Mới | L101: Partner (đọc) | M101: – | N101: Có / Có | O101: Tuấn | P101: 0.25 | Q101: 46353 | R101: 46353 | S101: 46353
... A109: 105 | B109: API-105 | C109: ZRDM-020 | D109: D | E109: Bút toán trích trước (accrual) | F109: Hạch toán trích trước | G109: POST | H109: /api/fi/accruals | I109: Z_RDM_FI_POST | J109: N.013 | K109: Mới | L109: Partner (ghi) | M109: Bắt buộc | N109: Có / Có | O109: Nam | P109: 0.25 | Q109: 46353 | R109: 46353 | S109: 46353
A110: 106 | B110: API-106 | C110: ZRDM-020 | D110: D | E110: Bút toán trích trước (accrual) | F110: Tra cứu chứng từ trích trước do RDM tạo | G110: GET | H110: /api/fi/accruals | I110: DB local + ZRDM_FI_DOC | J110: N.013 | K110: Mới | L110: Partner (đọc) | M110: – | N110: Có / – | O110: Nam | P110: 0.25 | Q110: 46353 | R110: 46354 | S110: 46353 | T110: Trễ 1 ngày – OT thứ Bảy
A111: 107 | B111: API-107 | C111: ZRDM-021 | D111: D | E111: Bút toán trích trước (accrual) | F111: Hoàn nhập 1 chứng từ khi sai sót | G111: POST | H111: /api/fi/accruals/{docNo}/reverse | I111: BAPI_ACC_DOCUMENT_REV_POST | J111: N.013 | K111: Điều chỉnh | L111: Partner (ghi) | M111: Bắt buộc | N111: Có / Có | O111: Tuấn | P111: 0.25 | Q111: 46347 | R111: 46347 | S111: 46353
A112: 108 | B112: API-108 | C112: ZRDM-022 | D112: D | E112: Hoàn nhập tự động đầu kỳ | F112: Chạy hoàn nhập tự động (thủ công / Hangfire) | G112: POST | H112: /api/fi/accruals/auto-reverse/run | I112: BAPI_ACC_DOCUMENT_REV_POST | J112: N.013 | K112: Mới | L112: Partner (ghi) | M112: Bắt buộc | N112: Có / Có | O112: Tuấn | P112: 0.5 | Q112: 46347 | R112: 46354 | S112: 46353 | T112: Trễ 1 ngày – OT thứ Bảy
A113: 109 | B113: API-109 | C113: ZRDM-022 | D113: D | E113: Hoàn nhập tự động đầu kỳ | F113: Lịch sử & kết quả các lần chạy | G113: GET | H113: /api/fi/accruals/auto-reverse/runs | I113: DB local | J113: – | K113: Mới | L113: Partner (đọc) | M113: – | N113: Có / – | O113: Tuấn | P113: 0.25 | Q113: 46354 | R113: 46354 | S113: 46353 | T113: Trễ 1 ngày – OT thứ Bảy
A114: 110 | B114: API-110 | C114: ZRDM-024 | D114: D | E114: Biên bản đối chiếu công nợ | F114: Lấy danh sách KH có biên bản theo kỳ | G114: GET | H114: /api/fi/ar-statements | I114: Z_RDM_AR_STMT_GET | J114: N.024 | K114: Mới | L114: Partner (đọc) | M114: – | N114: Có / Có | O114: Tuấn | P114: 0.25 | Q114: 46356 | R114: 46356 | S114: 46356
A115: 111 | B115: API-111 | C115: ZRDM-024 | D115: D | E115: Biên bản đối chiếu công nợ | F115: Lấy chi tiết biên bản 1 KH/kỳ | G115: GET | H115: /api/fi/ar-statements/{customer} | I115: Z_RDM_AR_STMT_GET | J115: N.024 | K115: Mới | L115: Partner (đọc) | M115: – | N115: Có / Có | O115: Tuấn | P115: 0.5 | Q115: 46356 | R115: 46356 | S115: 46356
A116: 112 | B116: API-112 | C116: ZRDM-024 | D116: D | E116: Biên bản đối chiếu công nợ | F116: Trích xuất hàng loạt theo kỳ (job nền) | G116: POST | H116: /api/fi/ar-statements/jobs/export | I116: Z_RDM_AR_STMT_GET | J116: N.024 | K116: Mới | L116: Partner (ghi) | M116: Bắt buộc | N116: Có / Có | O116: Tuấn | P116: 0.25 | Q116: 46356 | R116: 46356 | S116: 46356
B118: Thống kê
B119: Có sẵn | C119: =COUNTIF(K5:K116,B119) | D119: =SUMIF(K5:K116,B119,P5:P116)
B120: Điều chỉnh | C120: =COUNTIF(K5:K116,B120) | D120: =SUMIF(K5:K116,B120,P5:P116)
B121: Mới | C121: =COUNTIF(K5:K116,B121) | D121: =SUMIF(K5:K116,B121,P5:P116)
B122: Tổng | C122: =SUM(C119:C121) | D122: =SUM(D119:D121)

Sheet WBS chi tiết
A1: WBS CHI TIẾT – công việc, người làm, công, lịch
A2: Cột công (md) theo từng người; Tổng = công thức. Ngày bắt đầu/kết thúc do lịch tự động xếp theo năng lực. Dòng nền cam = kết thúc sau hạn SOW
A4: Mã | B4: Giai đoạn | C4: Mã SOW | D4: Công việc | E4: Sản phẩm bàn giao | F4: Chủ trì | G4: Loại | H4: Tuấn | I4: Nam | J4: Khang | K4: Sơn | L4: Hằng | M4: Tổng công | N4: Bắt đầu | O4: Kết thúc | P4: Số ngày LV | Q4: Phụ thuộc | R4: Tiêu chí hoàn thành | S4: Hạn SOW | T4: Trạng thái | U4: Hạng mục chi phí
A5: 0.1 | B5: P0 Khởi động & chốt yêu cầu | C5: Tất cả | D5: Kickoff: chốt phạm vi 24 đối tượng, kế hoạch 40 ngày, quy trình duyệt spec & change request | E5: Biên bản kickoff, kế hoạch baseline | F5: Tuấn | G5: Workshop/Test | H5: 0.5 | I5: 0.25 | J5: 0.25 | K5: 0.25 | L5: 0.25 | M5: =SUM(H5:L5) | N5: 46324 | O5: 46324 | P5: =NETWORKDAYS(N5,O5) | R5: Các bên xác nhận phạm vi & kế hoạch | T5: Chưa bắt đầu | U5: Phân tích & spec
A6: 0.2 | B6: P0 Khởi động & chốt yêu cầu | C6: Tất cả | D6: Kiểm tra môi trường: user RFC DEV930 (S_RFC, S_TCODE), NCo 3.1, SQL Server, server API, quyền transport | E6: Checklist môi trường | F6: Nam | G6: Workshop/Test | H6: 0.5 | I6: 0.5 | M6: =SUM(H6:L6) | N6: 46324 | O6: 46325 | P6: =NETWORKDAYS(N6,O6) | Q6: 0.1 | R6: RFC_PING + 1 BAPI đọc chạy thành công | T6: Chưa bắt đầu | U6: Phân tích & spec
A7: 0.3 | B7: P0 Khởi động & chốt yêu cầu | C7: 001, 004–012 | D7: Workshop SD: chốt open point (loại xe = CG3?, chiều VAT, logic "theo xe", định nghĩa sản lượng, credit Classic/FSCM, mã dịch vụ tạo HĐ hàng loạt) | E7: Decision log SD | F7: Hằng | G7: Workshop/Test | H7: 0.5 | I7: 0.25 | L7: 1 | M7: =SUM(H7:L7) | N7: 46325 | O7: 46329 | P7: =NETWORKDAYS(N7,O7) | Q7: 0.1 | R7: Mọi open point SD có quyết định + người chốt | T7: Chưa bắt đầu | U7: Phân tích & spec
A8: 0.4 | B8: P0 Khởi động & chốt yêu cầu | C8: 003, 013–024 | D8: Workshop FI: ma trận bút toán (doc type, posting key, tài khoản, đối tượng CO), quyết toán âm, % CK thanh toán trước, trường GAP tính lãi, accrual cho free-bag | E8: Ma trận bút toán FI + decision log FI | F8: Sơn | G8: Workshop/Test | H8: 0.5 | I8: 0.25 | J8: 0.25 | K8: 1 | M8: =SUM(H8:L8) | N8: 46325 | O8: 46329 | P8: =NETWORKDAYS(N8,O8) | Q8: 0.1 | R8: Ma trận bút toán được KT trưởng Tafico duyệt | T8: Chưa bắt đầu | U8: Phân tích & spec
A9: 0.5 | B9: P0 Khởi động & chốt yêu cầu | C9: Tất cả | D9: Mapping field từng API (input/output), bảng mã lỗi nghiệp vụ, sign-off BRD | E9: BRD + file mapping v1.0 | F9: Tuấn | G9: Workshop/Test | H9: 0.5 | K9: 0.25 | L9: 0.25 | M9: =SUM(H9:L9) | N9: 46329 | O9: 46330 | P9: =NETWORKDAYS(N9,O9) | Q9: 0.3, 0.4 | R9: File mapping được RDM & Tafico ký | T9: Chưa bắt đầu | U9: Phân tích & spec
A10: API-004 | B10: P1 Nền tảng: REST, JWT, Logging API + Logging trên SAP | C10: Chung | D10: GET /api/auth/users – Người dùng: Danh sách user | E10: Rà soát + test + Swagger | F10: Tuấn | G10: API | H10: 0.1 | M10: =SUM(H10:L10) | N10: 46325 | O10: 46325 | P10: =NETWORKDAYS(N10,O10) | Q10: 0.2 | R10: Đúng dữ liệu, phân trang, phân quyền đối tác | S10: 46339 | T10: Chưa bắt đầu | U10: Phát triển API
A11: API-006 | B11: P1 Nền tảng: REST, JWT, Logging API + Logging trên SAP | C11: Chung | D11: GET /api/postings/{id} – Chứng từ RDM: Tra cứu theo Id | E11: Rà soát + test + Swagger | F11: Tuấn | G11: API | H11: 0.1 | M11: =SUM(H11:L11) | N11: 46325 | O11: 46325 | P11: =NETWORKDAYS(N11,O11) | Q11: 0.2 | R11: Đúng dữ liệu, phân trang, phân quyền đối tác | S11: 46339 | T11: Chưa bắt đầu | U11: Phát triển API
A12: API-007 | B12: P1 Nền tảng: REST, JWT, Logging API + Logging trên SAP | C12: Chung | D12: GET /api/postings/{operation}/{requestId} – Chứng từ RDM: Tra cứu theo requestId | E12: Rà soát + test + Swagger | F12: Tuấn | G12: API | H12: 0.1 | M12: =SUM(H12:L12) | N12: 46325 | O12: 46325 | P12: =NETWORKDAYS(N12,O12) | Q12: 0.2 | R12: Đúng dữ liệu, phân trang, phân quyền đối tác | S12: 46339 | T12: Chưa bắt đầu | U12: Phát triển API
A13: API-008 | B13: P1 Nền tảng: REST, JWT, Logging API + Logging trên SAP | C13: Chung | D13: GET /api/postings – Chứng từ RDM: Tìm kiếm danh sách | E13: Rà soát + test + Swagger | F13: Tuấn | G13: API | H13: 0.1 | M13: =SUM(H13:L13) | N13: 46325 | O13: 46325 | P13: =NETWORKDAYS(N13,O13) | Q13: 0.2 | R13: Đúng dữ liệu, phân trang, phân quyền đối tác | S13: 46339 | T13: Chưa bắt đầu | U13: Phát triển API
A14: API-009 | B14: P1 Nền tảng: REST, JWT, Logging API + Logging trên SAP | C14: Chung | D14: GET /api/sap/ping – Kết nối SAP: Kiểm tra kết nối | E14: Rà soát + test + Swagger | F14: Tuấn | G14: API | H14: 0.1 | M14: =SUM(H14:L14) | N14: 46325 | O14: 46325 | P14: =NETWORKDAYS(N14,O14) | Q14: 0.2 | R14: Đúng dữ liệu, phân trang, phân quyền đối tác | S14: 46339 | T14: Chưa bắt đầu | U14: Phát triển API
A15: L.0 | B15: P1 Nền tảng: REST, JWT, Logging API + Logging trên SAP | C15: Tất cả | D15: Chuẩn ABAP: template FM RFC (RETURN, COMMIT/ROLLBACK, gọi log), quy ước đặt tên, code review, transport | E15: Coding guideline ABAP | F15: Nam | G15: ABAP | I15: 0.5 | M15: =SUM(H15:L15) | N15: 46325 | O15: 46325 | P15: =NETWORKDAYS(N15,O15) | Q15: 0.2 | R15: Nam & Khang dùng chung template | S15: 46339 | T15: Chưa bắt đầu | U15: Phát triển ABAP
A16: 1.1 | B16: P1 Nền tảng: REST, JWT, Logging API + Logging trên SAP | C16: Tất cả | D16: Thiết kế kiến trúc: chuẩn REST (resource/hành động, paging, ProblemDetails), bảng mã lỗi, idempotency requestId, quy tắc không retry lệnh ghi | E16: Tài liệu kiến trúc (SAD) | F16: Tuấn | G16: Thiết kế/Tài liệu | H16: 0.75 | M16: =SUM(H16:L16) | N16: 46328 | O16: 46328 | P16: =NETWORKDAYS(N16,O16) | Q16: 0.2 | R16: Techlead review đạt | S16: 46339 | T16: Chưa bắt đầu | U16: Kiến trúc & bảo mật
A17: L.1 | B17: P1 Nền tảng: REST, JWT, Logging API + Logging trên SAP | C17: Tất cả | D17: Logging SAP: bảng ZRDM_API_LOG (header) + ZRDM_API_LOGI (message), BAL object ZRDM / subobject theo SOW, FM Z_RDM_LOG_WRITE (nhận Correlation-Id, user RDM, payload rút gọn) | E17: Objects ABAP logging | F17: Nam | G17: ABAP | I17: 2 | M17: =SUM(H17:L17) | N17: 46328 | O17: 46330 | P17: =NETWORKDAYS(N17,O17) | Q17: L.0 | R17: Xem được log trên SLG1 & bảng Z | S17: 46339 | T17: Chưa bắt đầu | U17: Phát triển ABAP
A18: 1.2 | B18: P1 Nền tảng: REST, JWT, Logging API + Logging trên SAP | C18: Tất cả | D18: JWT: cấp/refresh token, role, phạm vi dữ liệu theo đối tác (sửa lỗi KH thấy full data), xoay khóa ký, khóa tài khoản | E18: Module Auth + test bảo mật | F18: Tuấn | G18: Thiết kế/Tài liệu | H18: 1.25 | M18: =SUM(H18:L18) | N18: 46329 | O18: 46330 | P18: =NETWORKDAYS(N18,O18) | Q18: 1.1 | R18: Sai/hết hạn token → 401; ngoài phạm vi → 403 | S18: 46339 | T18: Chưa bắt đầu | U18: Kiến trúc & bảo mật
A19: L.2 | B19: P1 Nền tảng: REST, JWT, Logging API + Logging trên SAP | C19: Tất cả | D19: Report ZRDM_LOG_VIEW (lọc SOW/ngày/user/Correlation-Id/trạng thái) + job dọn log quá hạn (SM36) | E19: Report ZRDM_LOG_VIEW | F19: Nam | G19: ABAP | I19: 0.75 | M19: =SUM(H19:L19) | N19: 46330 | O19: 46331 | P19: =NETWORKDAYS(N19,O19) | Q19: L.1 | R19: Tra cứu được log theo Correlation-Id | S19: 46339 | T19: Chưa bắt đầu | U19: Phát triển ABAP
A20: 1.3 | B20: P1 Nền tảng: REST, JWT, Logging API + Logging trên SAP | C20: Tất cả | D20: Logging API: Serilog (file + SQL), Correlation-Id xuyên suốt và truyền sang SAP, rdm.SapCallLog, che dữ liệu nhạy cảm, retention | E20: Logging API | F20: Tuấn | G20: Thiết kế/Tài liệu | H20: 0.5 | M20: =SUM(H20:L20) | N20: 46331 | O20: 46331 | P20: =NETWORKDAYS(N20,O20) | Q20: 1.1 | R20: Mỗi request truy được theo Correlation-Id | S20: 46339 | T20: Chưa bắt đầu | U20: Kiến trúc & bảo mật
A21: API-001 | B21: P1 Nền tảng: REST, JWT, Logging API + Logging trên SAP | C21: Chung | D21: POST /api/auth/token – Xác thực: Cấp token JWT | E21: Điều chỉnh + test + Swagger | F21: Tuấn | G21: API | H21: 0.25 | M21: =SUM(H21:L21) | N21: 46331 | O21: 46331 | P21: =NETWORKDAYS(N21,O21) | Q21: 1.1 | R21: Có requestId, log 2 phía, mã lỗi đúng | S21: 46339 | T21: Chưa bắt đầu | U21: Phát triển API
A22: API-002 | B22: P1 Nền tảng: REST, JWT, Logging API + Logging trên SAP | C22: Chung | D22: POST /api/auth/refresh – Xác thực: Làm mới token (refresh) | E22: Code mới + unit test + Swagger | F22: Tuấn | G22: API | H22: 0.25 | M22: =SUM(H22:L22) | N22: 46331 | O22: 46331 | P22: =NETWORKDAYS(N22,O22) | Q22: 1.1 | R22: Có requestId, log 2 phía, mã lỗi đúng | S22: 46339 | T22: Chưa bắt đầu | U22: Phát triển API
A23: L.3 | B23: P1 Nền tảng: REST, JWT, Logging API + Logging trên SAP | C23: Tất cả | D23: RFC Z_RDM_LOG_READ – đọc log SAP cho API quản trị | E23: FM RFC | F23: Nam | G23: ABAP | I23: 0.5 | M23: =SUM(H23:L23) | N23: 46331 | O23: 46331 | P23: =NETWORKDAYS(N23,O23) | Q23: L.1 | R23: API đọc được log SAP | S23: 46339 | T23: Chưa bắt đầu | U23: Phát triển ABAP
A24: API-003 | B24: P1 Nền tảng: REST, JWT, Logging API + Logging trên SAP | C24: Chung | D24: GET /api/auth/me – Xác thực: Thông tin user hiện tại + phạm vi dữ liệu | E24: Điều chỉnh + test + Swagger | F24: Tuấn | G24: API | H24: 0.1 | M24: =SUM(H24:L24) | N24: 46332 | O24: 46332 | P24: =NETWORKDAYS(N24,O24) | Q24: 1.1 | R24: Đúng dữ liệu, phân trang, phân quyền đối tác | S24: 46339 | T24: Chưa bắt đầu | U24: Phát triển API
A25: API-005 | B25: P1 Nền tảng: REST, JWT, Logging API + Logging trên SAP | C25: Chung | D25: PUT /api/auth/users/{username} – Người dùng: Tạo/sửa user, role, phạm vi đối tác | E25: Điều chỉnh + test + Swagger | F25: Tuấn | G25: API | H25: 0.25 | M25: =SUM(H25:L25) | N25: 46332 | O25: 46332 | P25: =NETWORKDAYS(N25,O25) | Q25: 1.1 | R25: Có requestId, log 2 phía, mã lỗi đúng | S25: 46339 | T25: Chưa bắt đầu | U25: Phát triển API
A26: API-010 | B26: P1 Nền tảng: REST, JWT, Logging API + Logging trên SAP | C26: Chung | D26: GET /api/admin/sap-calls – Log API→SAP: Danh sách log gọi SAP | E26: Rà soát + test + Swagger | F26: Tuấn | G26: API | H26: 0.1 | M26: =SUM(H26:L26) | N26: 46332 | O26: 46332 | P26: =NETWORKDAYS(N26,O26) | Q26: 0.2 | R26: Đúng dữ liệu, phân trang, phân quyền đối tác | S26: 46339 | T26: Chưa bắt đầu | U26: Phát triển API
A27: API-011 | B27: P1 Nền tảng: REST, JWT, Logging API + Logging trên SAP | C27: Chung | D27: GET /api/admin/sap-calls/{id} – Log API→SAP: Chi tiết 1 lần gọi | E27: Rà soát + test + Swagger | F27: Tuấn | G27: API | H27: 0.1 | M27: =SUM(H27:L27) | N27: 46332 | O27: 46332 | P27: =NETWORKDAYS(N27,O27) | Q27: 0.2 | R27: Đúng dữ liệu, phân trang, phân quyền đối tác | S27: 46339 | T27: Chưa bắt đầu | U27: Phát triển API
A28: API-012 | B28: P1 Nền tảng: REST, JWT, Logging API + Logging trên SAP | C28: Chung | D28: GET /api/admin/sap-logs – Log trên SAP: Danh sách log SAP (ZRDM_API_LOG) | E28: Code mới + unit test + Swagger | F28: Tuấn | G28: API | H28: 0.25 | M28: =SUM(H28:L28) | N28: 46339 | O28: 46339 | P28: =NETWORKDAYS(N28,O28) | Q28: L.3 | R28: Đúng dữ liệu, phân trang, phân quyền đối tác | S28: 46346 | T28: Chưa bắt đầu | U28: Phát triển API
A29: API-013 | B29: P1 Nền tảng: REST, JWT, Logging API + Logging trên SAP | C29: Chung | D29: GET /api/admin/sap-logs/{correlationId} – Log trên SAP: Log SAP theo Correlation-Id | E29: Code mới + unit test + Swagger | F29: Tuấn | G29: API | H29: 0.25 | M29: =SUM(H29:L29) | N29: 46339 | O29: 46342 | P29: =NETWORKDAYS(N29,O29) | Q29: L.3 | R29: Đúng dữ liệu, phân trang, phân quyền đối tác | S29: 46346 | T29: Chưa bắt đầu | U29: Phát triển API
A30: L.4 | B30: P1 Nền tảng: REST, JWT, Logging API + Logging trên SAP | C30: Tất cả | D30: Gắn logging SAP vào các FM đang có: Z_EFI011, Z_EFI009, Z_ESD012/013/014/015/016 | E30: Transport sửa FM | F30: Nam | G30: ABAP | I30: 1 | M30: =SUM(H30:L30) | N30: 46344 | O30: 46345 | P30: =NETWORKDAYS(N30,O30) | Q30: L.1 | R30: Mọi lời gọi từ RDM đều có log SAP | S30: 46353 | T30: Chưa bắt đầu | U30: Phát triển ABAP
A31: N.001 | B31: P2 Nhóm A – Master data (hạn 13/11) | C31: ZRDM-001 | D31: RFC Z_RDM_CUST_DELTA_GET: Sold-to/Ship-to + quan hệ KNVP thay đổi từ ngày (CDHDR/CDPOS), phân trang | E31: FM RFC | F31: Nam | G31: ABAP | I31: 1 | M31: =SUM(H31:L31) | N31: 46331 | O31: 46332 | P31: =NETWORKDAYS(N31,O31) | Q31: 0.3 | R31: Delta trả đúng bản ghi thay đổi | S31: 46339 | T31: Chưa bắt đầu | U31: Phát triển ABAP
A32: API-014 | B32: P2 Nhóm A – Master data (hạn 13/11) | C32: ZRDM-001 | D32: POST /api/master-data/sold-to/sync – Sold-to: Đồng bộ từ SAP (full + delta) | E32: Điều chỉnh + test + Swagger | F32: Tuấn | G32: API | H32: 0.5 | M32: =SUM(H32:L32) | N32: 46332 | O32: 46335 | P32: =NETWORKDAYS(N32,O32) | Q32: N.001 | R32: Có requestId, log 2 phía, mã lỗi đúng | S32: 46339 | T32: Chưa bắt đầu | U32: Phát triển API
A33: API-015 | B33: P2 Nhóm A – Master data (hạn 13/11) | C33: ZRDM-001 | D33: GET /api/master-data/sold-to – Sold-to: Lấy danh sách (lọc, phân trang, changedSince) | E33: Điều chỉnh + test + Swagger | F33: Tuấn | G33: API | H33: 0.25 | M33: =SUM(H33:L33) | N33: 46335 | O33: 46335 | P33: =NETWORKDAYS(N33,O33) | Q33: 1.1 | R33: Đúng dữ liệu, phân trang, phân quyền đối tác | S33: 46339 | T33: Chưa bắt đầu | U33: Phát triển API
A34: API-016 | B34: P2 Nhóm A – Master data (hạn 13/11) | C34: ZRDM-001 | D34: GET /api/master-data/sold-to/{customer} – Sold-to: Lấy chi tiết 1 KH | E34: Rà soát + test + Swagger | F34: Tuấn | G34: API | H34: 0.05 | M34: =SUM(H34:L34) | N34: 46335 | O34: 46335 | P34: =NETWORKDAYS(N34,O34) | Q34: 0.2 | R34: Đúng dữ liệu, phân trang, phân quyền đối tác | S34: 46339 | T34: Chưa bắt đầu | U34: Phát triển API
A35: API-017 | B35: P2 Nhóm A – Master data (hạn 13/11) | C35: ZRDM-001 | D35: POST /api/master-data/ship-to/sync – Ship-to: Đồng bộ từ SAP (full + delta) | E35: Điều chỉnh + test + Swagger | F35: Tuấn | G35: API | H35: 0.25 | M35: =SUM(H35:L35) | N35: 46335 | O35: 46335 | P35: =NETWORKDAYS(N35,O35) | Q35: N.001 | R35: Có requestId, log 2 phía, mã lỗi đúng | S35: 46339 | T35: Chưa bắt đầu | U35: Phát triển API
A36: API-018 | B36: P2 Nhóm A – Master data (hạn 13/11) | C36: ZRDM-001 | D36: GET /api/master-data/ship-to – Ship-to: Lấy danh sách | E36: Điều chỉnh + test + Swagger | F36: Tuấn | G36: API | H36: 0.1 | M36: =SUM(H36:L36) | N36: 46335 | O36: 46335 | P36: =NETWORKDAYS(N36,O36) | Q36: 1.1 | R36: Đúng dữ liệu, phân trang, phân quyền đối tác | S36: 46339 | T36: Chưa bắt đầu | U36: Phát triển API
A37: API-019 | B37: P2 Nhóm A – Master data (hạn 13/11) | C37: ZRDM-001 | D37: GET /api/master-data/ship-to/{customer} – Ship-to: Lấy chi tiết 1 ship-to | E37: Rà soát + test + Swagger | F37: Tuấn | G37: API | H37: 0.05 | M37: =SUM(H37:L37) | N37: 46335 | O37: 46335 | P37: =NETWORKDAYS(N37,O37) | Q37: 0.2 | R37: Đúng dữ liệu, phân trang, phân quyền đối tác | S37: 46339 | T37: Chưa bắt đầu | U37: Phát triển API
A38: API-020 | B38: P2 Nhóm A – Master data (hạn 13/11) | C38: ZRDM-001 | D38: POST /api/master-data/sold-to-ship-to/sync – Quan hệ Sold-to ↔ Ship-to: Đồng bộ từ SAP | E38: Rà soát + test + Swagger | F38: Tuấn | G38: API | H38: 0.1 | M38: =SUM(H38:L38) | N38: 46335 | O38: 46335 | P38: =NETWORKDAYS(N38,O38) | Q38: 0.2 | R38: Có requestId, log 2 phía, mã lỗi đúng | S38: 46339 | T38: Chưa bắt đầu | U38: Phát triển API
A39: API-021 | B39: P2 Nhóm A – Master data (hạn 13/11) | C39: ZRDM-001 | D39: GET /api/master-data/sold-to-ship-to – Quan hệ Sold-to ↔ Ship-to: Lấy danh sách | E39: Rà soát + test + Swagger | F39: Tuấn | G39: API | H39: 0.05 | M39: =SUM(H39:L39) | N39: 46335 | O39: 46335 | P39: =NETWORKDAYS(N39,O39) | Q39: 0.2 | R39: Đúng dữ liệu, phân trang, phân quyền đối tác | S39: 46339 | T39: Chưa bắt đầu | U39: Phát triển API
A40: API-022 | B40: P2 Nhóm A – Master data (hạn 13/11) | C40: ZRDM-001 | D40: POST /api/master-data/sales-orgs/sync – Sales Org: Đồng bộ từ SAP | E40: Rà soát + test + Swagger | F40: Tuấn | G40: API | H40: 0.1 | M40: =SUM(H40:L40) | N40: 46335 | O40: 46335 | P40: =NETWORKDAYS(N40,O40) | Q40: 0.2 | R40: Có requestId, log 2 phía, mã lỗi đúng | S40: 46339 | T40: Chưa bắt đầu | U40: Phát triển API
A41: API-023 | B41: P2 Nhóm A – Master data (hạn 13/11) | C41: ZRDM-001 | D41: GET /api/master-data/sales-orgs – Sales Org: Lấy danh sách | E41: Rà soát + test + Swagger | F41: Tuấn | G41: API | H41: 0.05 | M41: =SUM(H41:L41) | N41: 46336 | O41: 46336 | P41: =NETWORKDAYS(N41,O41) | Q41: 0.2 | R41: Đúng dữ liệu, phân trang, phân quyền đối tác | S41: 46339 | T41: Chưa bắt đầu | U41: Phát triển API
A42: API-024 | B42: P2 Nhóm A – Master data (hạn 13/11) | C42: ZRDM-001 | D42: POST /api/master-data/distribution-channels/sync – Kênh phân phối: Đồng bộ từ SAP | E42: Code mới + unit test + Swagger | F42: Tuấn | G42: API | H42: 0.25 | M42: =SUM(H42:L42) | N42: 46336 | O42: 46336 | P42: =NETWORKDAYS(N42,O42) | Q42: 1.1 | R42: Có requestId, log 2 phía, mã lỗi đúng | S42: 46339 | T42: Chưa bắt đầu | U42: Phát triển API
A43: API-025 | B43: P2 Nhóm A – Master data (hạn 13/11) | C43: ZRDM-001 | D43: GET /api/master-data/distribution-channels – Kênh phân phối: Lấy danh sách | E43: Code mới + unit test + Swagger | F43: Tuấn | G43: API | H43: 0.25 | M43: =SUM(H43:L43) | N43: 46336 | O43: 46336 | P43: =NETWORKDAYS(N43,O43) | Q43: 1.1 | R43: Đúng dữ liệu, phân trang, phân quyền đối tác | S43: 46339 | T43: Chưa bắt đầu | U43: Phát triển API
... A63: API-045 | B63: P2 Nhóm A – Master data (hạn 13/11) | C63: ZRDM-002 | D63: GET /api/master-data/material-groups – Material Group: Lấy danh sách | E63: Rà soát + test + Swagger | F63: Tuấn | G63: API | H63: 0.05 | M63: =SUM(H63:L63) | N63: 46337 | O63: 46337 | P63: =NETWORKDAYS(N63,O63) | Q63: 0.2 | R63: Đúng dữ liệu, phân trang, phân quyền đối tác | S63: 46339 | T63: Chưa bắt đầu | U63: Phát triển API
A64: A.T | B64: P2 Nhóm A – Master data (hạn 13/11) | C64: ZRDM-001–003 | D64: Test nhóm A: integration DEV930, đối soát số bản ghi với SAP, bàn giao nhóm A | E64: Báo cáo test nhóm A | F64: Tuấn | G64: Workshop/Test | H64: 0.5 | I64: 0.25 | K64: 0.25 | L64: 0.25 | M64: =SUM(H64:L64) | N64: 46338 | O64: 46339 | P64: =NETWORKDAYS(N64,O64) | Q64: API nhóm A | R64: 100% test case pass – bàn giao 13/11 | T64: Chưa bắt đầu | U64: Kiểm thử
A65: API-046 | B65: P2 Nhóm A – Master data (hạn 13/11) | C65: ZRDM-002 | D65: POST /api/master-data/material-types/sync – Material Type: Đồng bộ từ SAP | E65: Rà soát + test + Swagger | F65: Tuấn | G65: API | H65: 0.1 | M65: =SUM(H65:L65) | N65: 46338 | O65: 46338 | P65: =NETWORKDAYS(N65,O65) | Q65: 0.2 | R65: Có requestId, log 2 phía, mã lỗi đúng | S65: 46339 | T65: Chưa bắt đầu | U65: Phát triển API
A66: API-047 | B66: P2 Nhóm A – Master data (hạn 13/11) | C66: ZRDM-002 | D66: GET /api/master-data/material-types – Material Type: Lấy danh sách | E66: Rà soát + test + Swagger | F66: Tuấn | G66: API | H66: 0.05 | M66: =SUM(H66:L66) | N66: 46338 | O66: 46338 | P66: =NETWORKDAYS(N66,O66) | Q66: 0.2 | R66: Đúng dữ liệu, phân trang, phân quyền đối tác | S66: 46339 | T66: Chưa bắt đầu | U66: Phát triển API
A67: API-048 | B67: P2 Nhóm A – Master data (hạn 13/11) | C67: ZRDM-002 | D67: POST /api/master-data/divisions/sync – Division: Đồng bộ từ SAP | E67: Rà soát + test + Swagger | F67: Tuấn | G67: API | H67: 0.1 | M67: =SUM(H67:L67) | N67: 46338 | O67: 46338 | P67: =NETWORKDAYS(N67,O67) | Q67: 0.2 | R67: Có requestId, log 2 phía, mã lỗi đúng | S67: 46339 | T67: Chưa bắt đầu | U67: Phát triển API
A68: API-049 | B68: P2 Nhóm A – Master data (hạn 13/11) | C68: ZRDM-002 | D68: GET /api/master-data/divisions – Division: Lấy danh sách | E68: Rà soát + test + Swagger | F68: Tuấn | G68: API | H68: 0.05 | M68: =SUM(H68:L68) | N68: 46338 | O68: 46338 | P68: =NETWORKDAYS(N68,O68) | Q68: 0.2 | R68: Đúng dữ liệu, phân trang, phân quyền đối tác | S68: 46339 | T68: Chưa bắt đầu | U68: Phát triển API
A69: API-050 | B69: P2 Nhóm A – Master data (hạn 13/11) | C69: ZRDM-002 | D69: POST /api/master-data/plants/sync – Plant: Đồng bộ từ SAP | E69: Rà soát + test + Swagger | F69: Tuấn | G69: API | H69: 0.1 | M69: =SUM(H69:L69) | N69: 46338 | O69: 46338 | P69: =NETWORKDAYS(N69,O69) | Q69: 0.2 | R69: Có requestId, log 2 phía, mã lỗi đúng | S69: 46339 | T69: Chưa bắt đầu | U69: Phát triển API
A70: API-051 | B70: P2 Nhóm A – Master data (hạn 13/11) | C70: ZRDM-002 | D70: GET /api/master-data/plants – Plant: Lấy danh sách | E70: Rà soát + test + Swagger | F70: Tuấn | G70: API | H70: 0.05 | M70: =SUM(H70:L70) | N70: 46338 | O70: 46338 | P70: =NETWORKDAYS(N70,O70) | Q70: 0.2 | R70: Đúng dữ liệu, phân trang, phân quyền đối tác | S70: 46339 | T70: Chưa bắt đầu | U70: Phát triển API
A71: API-052 | B71: P2 Nhóm A – Master data (hạn 13/11) | C71: ZRDM-003 | D71: POST /api/master-data/gl-accounts/sync – Tài khoản GL (COA 1000): Đồng bộ + đối soát khóa/xóa | E71: Điều chỉnh + test + Swagger | F71: Tuấn | G71: API | H71: 0.25 | M71: =SUM(H71:L71) | N71: 46338 | O71: 46338 | P71: =NETWORKDAYS(N71,O71) | Q71: 1.1 | R71: Có requestId, log 2 phía, mã lỗi đúng | S71: 46339 | T71: Chưa bắt đầu | U71: Phát triển API
A72: API-053 | B72: P2 Nhóm A – Master data (hạn 13/11) | C72: ZRDM-003 | D72: GET /api/master-data/gl-accounts – Tài khoản GL (COA 1000): Lấy danh sách | E72: Rà soát + test + Swagger | F72: Tuấn | G72: API | H72: 0.05 | M72: =SUM(H72:L72) | N72: 46338 | O72: 46338 | P72: =NETWORKDAYS(N72,O72) | Q72: 0.2 | R72: Đúng dữ liệu, phân trang, phân quyền đối tác | S72: 46339 | T72: Chưa bắt đầu | U72: Phát triển API
A73: API-054 | B73: P2 Nhóm A – Master data (hạn 13/11) | C73: ZRDM-003 | D73: POST /api/master-data/cost-centers/sync – Cost Center (G100): Đồng bộ + đối soát khóa/xóa | E73: Điều chỉnh + test + Swagger | F73: Tuấn | G73: API | H73: 0.25 | M73: =SUM(H73:L73) | N73: 46339 | O73: 46339 | P73: =NETWORKDAYS(N73,O73) | Q73: 1.1 | R73: Có requestId, log 2 phía, mã lỗi đúng | S73: 46339 | T73: Chưa bắt đầu | U73: Phát triển API
A74: API-055 | B74: P2 Nhóm A – Master data (hạn 13/11) | C74: ZRDM-003 | D74: GET /api/master-data/cost-centers – Cost Center (G100): Lấy danh sách | E74: Rà soát + test + Swagger | F74: Tuấn | G74: API | H74: 0.05 | M74: =SUM(H74:L74) | N74: 46339 | O74: 46339 | P74: =NETWORKDAYS(N74,O74) | Q74: 0.2 | R74: Đúng dữ liệu, phân trang, phân quyền đối tác | S74: 46339 | T74: Chưa bắt đầu | U74: Phát triển API
A75: API-077 | B75: P3 Nhóm B – Giá, VAT, hợp đồng, tín dụng, free-bag (hạn 20/11) | C75: ZRDM-006 | D75: POST /api/sd/contracts/change – Hợp đồng bán hàng: Sửa HĐ | E75: Rà soát + test + Swagger | F75: Tuấn | G75: API | H75: 0.1 | M75: =SUM(H75:L75) | N75: 46326 | O75: 46326 | P75: =NETWORKDAYS(N75,O75) | Q75: 0.2 | R75: Có requestId, log 2 phía, mã lỗi đúng | S75: 46346 | T75: Chưa bắt đầu | U75: Phát triển API
A76: API-078 | B76: P3 Nhóm B – Giá, VAT, hợp đồng, tín dụng, free-bag (hạn 20/11) | C76: ZRDM-006 | D76: POST /api/sd/contracts/approve – Hợp đồng bán hàng: Duyệt HĐ | E76: Rà soát + test + Swagger | F76: Tuấn | G76: API | H76: 0.1 | M76: =SUM(H76:L76) | N76: 46326 | O76: 46326 | P76: =NETWORKDAYS(N76,O76) | Q76: 0.2 | R76: Có requestId, log 2 phía, mã lỗi đúng | S76: 46346 | T76: Chưa bắt đầu | U76: Phát triển API
... A78: API-080 | B78: P3 Nhóm B – Giá, VAT, hợp đồng, tín dụng, free-bag (hạn 20/11) | C78: ZRDM-007 | D78: GET /api/customer-credits/{customer} – Hạn mức tín dụng (KNKK): Lấy hạn mức 1 KH theo KKBER | E78: Rà soát + test + Swagger | F78: Tuấn | G78: API | H78: 0.1 | M78: =SUM(H78:L78) | N78: 46326 | O78: 46326 | P78: =NETWORKDAYS(N78,O78) | Q78: 0.2 | R78: Đúng dữ liệu, phân trang, phân quyền đối tác | S78: 46346 | T78: Chưa bắt đầu | U78: Phát triển API
A79: B.S | B79: P3 Nhóm B – Giá, VAT, hợp đồng, tín dụng, free-bag (hạn 20/11) | C79: ZRDM-004/005 | D79: Spec giá: ZVLP/ZVDI (A990), ZVIV (A991), ZMIN (A912/A919) – khóa điều kiện, hiệu lực, release status, quy tắc trùng/overlap, test case nghiệp vụ | E79: Spec giá + bộ test case | F79: Hằng | G79: Workshop/Test | I79: 0.25 | L79: 1 | M79: =SUM(H79:L79) | N79: 46329 | O79: 46331 | P79: =NETWORKDAYS(N79,O79) | Q79: 0.3 | R79: Spec được Tafico duyệt | T79: Chưa bắt đầu | U79: Phân tích & spec
A80: B.S2 | B80: P3 Nhóm B – Giá, VAT, hợp đồng, tín dụng, free-bag (hạn 20/11) | C80: ZRDM-006/009 | D80: Spec chi tiết chương trình free-bag "theo xe" và hợp đồng bán hàng (lấy/tạo hàng loạt) + test case | E80: Spec SD nhóm B + test case | F80: Hằng | G80: Workshop/Test | L80: 0.75 | M80: =SUM(H80:L80) | N80: 46329 | O80: 46331 | P80: =NETWORKDAYS(N80,O80) | Q80: 0.3 | R80: Spec được Tafico duyệt | T80: Chưa bắt đầu | U80: Phân tích & spec
A81: N.004 | B81: P3 Nhóm B – Giá, VAT, hợp đồng, tín dụng, free-bag (hạn 20/11) | C81: ZRDM-004 | D81: Hoàn thiện Z_ESD016 (bọc BAPI_PRICES_CONDITIONS): kiểm tra trùng/overlap A990/A991/A912/A919, release status, trả mã lỗi chuẩn, log SAP | E81: FM Z_ESD016 + transport | F81: Nam | G81: ABAP | I81: 3 | M81: =SUM(H81:L81) | N81: 46332 | O81: 46337 | P81: =NETWORKDAYS(N81,O81) | Q81: B.S | R81: Không tạo được bản ghi chồng hiệu lực | S81: 46346 | T81: Chưa bắt đầu | U81: Phát triển ABAP
A82: N.009 | B82: P3 Nhóm B – Giá, VAT, hợp đồng, tín dụng, free-bag (hạn 20/11) | C82: ZRDM-009 | D82: Tách Z_ESD012 → Z_RDM_FREEGOODS_MAINTAIN: tạo/sửa/hủy hiệu lực chương trình free-bag, logic "theo xe" | E82: FM RFC | F82: Nam | G82: ABAP | I82: 2 | M82: =SUM(H82:L82) | N82: 46337 | O82: 46339 | P82: =NETWORKDAYS(N82,O82) | Q82: B.S2 | R82: Kiểm tra trên VBN3 đúng | S82: 46346 | T82: Chưa bắt đầu | U82: Phát triển ABAP
A83: API-081 | B83: P3 Nhóm B – Giá, VAT, hợp đồng, tín dụng, free-bag (hạn 20/11) | C83: ZRDM-009 | D83: POST /api/sd/freebag-programs – Chương trình free-bag: Tạo 1 chương trình | E83: Code mới + unit test + Swagger | F83: Tuấn | G83: API | H83: 0.5 | M83: =SUM(H83:L83) | N83: 46340 | O83: 46340 | P83: =NETWORKDAYS(N83,O83) | Q83: N.009 | R83: Có requestId, log 2 phía, mã lỗi đúng | S83: 46346 | T83: Chưa bắt đầu | U83: Phát triển API
A84: API-082 | B84: P3 Nhóm B – Giá, VAT, hợp đồng, tín dụng, free-bag (hạn 20/11) | C84: ZRDM-009 | D84: POST /api/sd/freebag-programs/jobs/create – Chương trình free-bag: Tạo nhiều chương trình (job nền) | E84: Code mới + unit test + Swagger | F84: Tuấn | G84: API | H84: 0.25 | M84: =SUM(H84:L84) | N84: 46340 | O84: 46340 | P84: =NETWORKDAYS(N84,O84) | Q84: N.009 | R84: Có requestId, log 2 phía, mã lỗi đúng | S84: 46346 | T84: Chưa bắt đầu | U84: Phát triển API
A85: API-083 | B85: P3 Nhóm B – Giá, VAT, hợp đồng, tín dụng, free-bag (hạn 20/11) | C85: ZRDM-009 | D85: POST /api/sd/freebag-programs/change – Chương trình free-bag: Sửa chương trình | E85: Code mới + unit test + Swagger | F85: Tuấn | G85: API | H85: 0.25 | M85: =SUM(H85:L85) | N85: 46340 | O85: 46340 | P85: =NETWORKDAYS(N85,O85) | Q85: N.009 | R85: Có requestId, log 2 phía, mã lỗi đúng | S85: 46346 | T85: Chưa bắt đầu | U85: Phát triển API
A86: API-056 | B86: P3 Nhóm B – Giá, VAT, hợp đồng, tín dụng, free-bag (hạn 20/11) | C86: ZRDM-004 | D86: POST /api/sd/prices/check – Bảng giá (ZVLP/ZVDI/ZMIN/ZVIV): Kiểm tra tồn tại / trùng / overlap | E86: Điều chỉnh + test + Swagger | F86: Tuấn | G86: API | H86: 0.25 | M86: =SUM(H86:L86) | N86: 46342 | O86: 46342 | P86: =NETWORKDAYS(N86,O86) | Q86: N.004 | R86: Có requestId, log 2 phía, mã lỗi đúng | S86: 46346 | T86: Chưa bắt đầu | U86: Phát triển API
A87: API-057 | B87: P3 Nhóm B – Giá, VAT, hợp đồng, tín dụng, free-bag (hạn 20/11) | C87: ZRDM-004 | D87: POST /api/sd/prices-bapi – Bảng giá: Tạo 1 bảng giá | E87: Điều chỉnh + test + Swagger | F87: Tuấn | G87: API | H87: 0.25 | M87: =SUM(H87:L87) | N87: 46342 | O87: 46342 | P87: =NETWORKDAYS(N87,O87) | Q87: N.004 | R87: Có requestId, log 2 phía, mã lỗi đúng | S87: 46346 | T87: Chưa bắt đầu | U87: Phát triển API
A88: API-058 | B88: P3 Nhóm B – Giá, VAT, hợp đồng, tín dụng, free-bag (hạn 20/11) | C88: ZRDM-004 | D88: POST /api/sd/prices-bapi/jobs/create – Bảng giá: Tạo nhiều bảng giá (job nền) | E88: Điều chỉnh + test + Swagger | F88: Tuấn | G88: API | H88: 0.25 | M88: =SUM(H88:L88) | N88: 46342 | O88: 46342 | P88: =NETWORKDAYS(N88,O88) | Q88: N.004 | R88: Có requestId, log 2 phía, mã lỗi đúng | S88: 46346 | T88: Chưa bắt đầu | U88: Phát triển API
A89: API-059 | B89: P3 Nhóm B – Giá, VAT, hợp đồng, tín dụng, free-bag (hạn 20/11) | C89: ZRDM-004 | D89: POST /api/sd/prices-bapi/change – Bảng giá: Sửa 1 bảng giá | E89: Điều chỉnh + test + Swagger | F89: Tuấn | G89: API | H89: 0.25 | M89: =SUM(H89:L89) | N89: 46342 | O89: 46343 | P89: =NETWORKDAYS(N89,O89) | Q89: N.004 | R89: Có requestId, log 2 phía, mã lỗi đúng | S89: 46346 | T89: Chưa bắt đầu | U89: Phát triển API
A90: N.006a | B90: P3 Nhóm B – Giá, VAT, hợp đồng, tín dụng, free-bag (hạn 20/11) | C90: ZRDM-006 | D90: RFC Z_RDM_CONTRACT_GET: header/item/partner/điều kiện HĐ phục vụ xuất mẫu biểu + danh sách HĐ theo KH/ngày | E90: FM RFC | F90: Nam | G90: ABAP | I90: 1 | M90: =SUM(H90:L90) | N90: 46342 | O90: 46343 | P90: =NETWORKDAYS(N90,O90) | Q90: B.S2 | R90: Đủ field theo mapping mẫu biểu | S90: 46346 | T90: Chưa bắt đầu | U90: Phát triển ABAP
A91: N.009b | B91: P3 Nhóm B – Giá, VAT, hợp đồng, tín dụng, free-bag (hạn 20/11) | C91: ZRDM-009 | D91: RFC Z_RDM_FREEGOODS_GET: đọc chương trình free-bag (KOTN*/KONDN/KONDNS) | E91: FM RFC | F91: Nam | G91: ABAP | I91: 0.5 | M91: =SUM(H91:L91) | N91: 46342 | O91: 46342 | P91: =NETWORKDAYS(N91,O91) | Q91: N.009 | R91: Dữ liệu khớp VBN3 | S91: 46346 | T91: Chưa bắt đầu | U91: Phát triển ABAP
A92: API-060 | B92: P3 Nhóm B – Giá, VAT, hợp đồng, tín dụng, free-bag (hạn 20/11) | C92: ZRDM-004 | D92: POST /api/sd/prices-bapi/jobs/change – Bảng giá: Sửa nhiều bảng giá (job nền) | E92: Rà soát + test + Swagger | F92: Tuấn | G92: API | H92: 0.1 | M92: =SUM(H92:L92) | N92: 46343 | O92: 46343 | P92: =NETWORKDAYS(N92,O92) | Q92: N.004 | R92: Có requestId, log 2 phía, mã lỗi đúng | S92: 46346 | T92: Chưa bắt đầu | U92: Phát triển API
A93: API-061 | B93: P3 Nhóm B – Giá, VAT, hợp đồng, tín dụng, free-bag (hạn 20/11) | C93: ZRDM-004 | D93: POST /api/sd/prices-bapi/approve – Bảng giá: Duyệt 1 bảng giá | E93: Rà soát + test + Swagger | F93: Tuấn | G93: API | H93: 0.1 | M93: =SUM(H93:L93) | N93: 46343 | O93: 46343 | P93: =NETWORKDAYS(N93,O93) | Q93: N.004 | R93: Có requestId, log 2 phía, mã lỗi đúng | S93: 46346 | T93: Chưa bắt đầu | U93: Phát triển API
A94: API-062 | B94: P3 Nhóm B – Giá, VAT, hợp đồng, tín dụng, free-bag (hạn 20/11) | C94: ZRDM-004 | D94: POST /api/sd/prices-bapi/jobs/approve – Bảng giá: Duyệt nhiều bảng giá (job nền) | E94: Rà soát + test + Swagger | F94: Tuấn | G94: API | H94: 0.1 | M94: =SUM(H94:L94) | N94: 46343 | O94: 46343 | P94: =NETWORKDAYS(N94,O94) | Q94: N.004 | R94: Có requestId, log 2 phía, mã lỗi đúng | S94: 46346 | T94: Chưa bắt đầu | U94: Phát triển API
A95: API-063 | B95: P3 Nhóm B – Giá, VAT, hợp đồng, tín dụng, free-bag (hạn 20/11) | C95: ZRDM-004 | D95: POST /api/sd/prices-bapi/unapprove – Bảng giá: Bỏ duyệt 1 bảng giá | E95: Rà soát + test + Swagger | F95: Tuấn | G95: API | H95: 0.1 | M95: =SUM(H95:L95) | N95: 46343 | O95: 46343 | P95: =NETWORKDAYS(N95,O95) | Q95: N.004 | R95: Có requestId, log 2 phía, mã lỗi đúng | S95: 46346 | T95: Chưa bắt đầu | U95: Phát triển API
A96: API-064 | B96: P3 Nhóm B – Giá, VAT, hợp đồng, tín dụng, free-bag (hạn 20/11) | C96: ZRDM-004 | D96: POST /api/sd/prices-bapi/jobs/unapprove – Bảng giá: Bỏ duyệt nhiều bảng giá (job nền) | E96: Rà soát + test + Swagger | F96: Tuấn | G96: API | H96: 0.1 | M96: =SUM(H96:L96) | N96: 46343 | O96: 46343 | P96: =NETWORKDAYS(N96,O96) | Q96: N.004 | R96: Có requestId, log 2 phía, mã lỗi đúng | S96: 46346 | T96: Chưa bắt đầu | U96: Phát triển API
A97: API-065 | B97: P3 Nhóm B – Giá, VAT, hợp đồng, tín dụng, free-bag (hạn 20/11) | C97: ZRDM-004 | D97: POST /api/sd/prices-bapi/invalidate – Bảng giá: Hủy hiệu lực 1 bảng giá | E97: Rà soát + test + Swagger | F97: Tuấn | G97: API | H97: 0.1 | M97: =SUM(H97:L97) | N97: 46343 | O97: 46343 | P97: =NETWORKDAYS(N97,O97) | Q97: N.004 | R97: Có requestId, log 2 phía, mã lỗi đúng | S97: 46346 | T97: Chưa bắt đầu | U97: Phát triển API
A98: API-066 | B98: P3 Nhóm B – Giá, VAT, hợp đồng, tín dụng, free-bag (hạn 20/11) | C98: ZRDM-004 | D98: POST /api/sd/prices-bapi/jobs/invalidate – Bảng giá: Hủy hiệu lực nhiều bảng giá (job nền) | E98: Rà soát + test + Swagger | F98: Tuấn | G98: API | H98: 0.1 | M98: =SUM(H98:L98) | N98: 46343 | O98: 46343 | P98: =NETWORKDAYS(N98,O98) | Q98: N.004 | R98: Có requestId, log 2 phía, mã lỗi đúng | S98: 46346 | T98: Chưa bắt đầu | U98: Phát triển API
A99: API-067 | B99: P3 Nhóm B – Giá, VAT, hợp đồng, tín dụng, free-bag (hạn 20/11) | C99: ZRDM-004 | D99: POST /api/sd/prices/copy-with-vat – Bảng giá: Tạo bảng giá mới từ bảng giá cũ theo VAT% | E99: Điều chỉnh + test + Swagger | F99: Tuấn | G99: API | H99: 0.25 | M99: =SUM(H99:L99) | N99: 46343 | O99: 46343 | P99: =NETWORKDAYS(N99,O99) | Q99: N.004 | R99: Có requestId, log 2 phía, mã lỗi đúng | S99: 46346 | T99: Chưa bắt đầu | U99: Phát triển API
A100: N.006b | B100: P3 Nhóm B – Giá, VAT, hợp đồng, tín dụng, free-bag (hạn 20/11) | C100: ZRDM-006 | D100: Tách Z_ESD013 → Z_RDM_CONTRACT_CREATE (bản RDM 2026, chế độ hàng loạt, trả kết quả từng dòng) | E100: FM RFC | F100: Nam | G100: ABAP | I100: 1 | M100: =SUM(H100:L100) | N100: 46343 | O100: 46344 | P100: =NETWORKDAYS(N100,O100) | Q100: B.S2 | R100: Hàng loạt: lỗi dòng nào báo dòng đó | S100: 46346 | T100: Chưa bắt đầu | U100: Phát triển ABAP
A101: API-068 | B101: P3 Nhóm B – Giá, VAT, hợp đồng, tín dụng, free-bag (hạn 20/11) | C101: ZRDM-004 | D101: GET /api/sd/prices – Bảng giá: Lấy bảng giá (lọc theo khóa điều kiện, hiệu lực) | E101: Điều chỉnh + test + Swagger | F101: Tuấn | G101: API | H101: 0.25 | M101: =SUM(H101:L101) | N101: 46344 | O101: 46344 | P101: =NETWORKDAYS(N101,O101) | Q101: 1.1 | R101: Đúng dữ liệu, phân trang, phân quyền đối tác | S101: 46346 | T101: Chưa bắt đầu | U101: Phát triển API
A102: API-069 | B102: P3 Nhóm B – Giá, VAT, hợp đồng, tín dụng, free-bag (hạn 20/11) | C102: ZRDM-004 | D102: GET /api/sd/prices-bapi/jobs/{operation}/{requestId} – Job bảng giá: Trạng thái / kết quả job theo requestId | E102: Rà soát + test + Swagger | F102: Tuấn | G102: API | H102: 0.1 | M102: =SUM(H102:L102) | N102: 46344 | O102: 46344 | P102: =NETWORKDAYS(N102,O102) | Q102: 0.2 | R102: Đúng dữ liệu, phân trang, phân quyền đối tác | S102: 46346 | T102: Chưa bắt đầu | U102: Phát triển API
A103: API-070 | B103: P3 Nhóm B – Giá, VAT, hợp đồng, tín dụng, free-bag (hạn 20/11) | C103: ZRDM-005 | D103: POST /api/mm/material-tax-classification – Phân loại thuế vật tư (TAXM1): Cập nhật TAXM1 cho danh sách vật tư | E103: Rà soát + test + Swagger | F103: Tuấn | G103: API | H103: 0.1 | M103: =SUM(H103:L103) | N103: 46344 | O103: 46344 | P103: =NETWORKDAYS(N103,O103) | Q103: 0.2 | R103: Có requestId, log 2 phía, mã lỗi đúng | S103: 46346 | T103: Chưa bắt đầu | U103: Phát triển API
A104: API-071 | B104: P3 Nhóm B – Giá, VAT, hợp đồng, tín dụng, free-bag (hạn 20/11) | C104: ZRDM-005 | D104: GET /api/mm/material-tax-classification – Phân loại thuế vật tư (TAXM1): Lấy TAXM1 theo vật tư | E104: Code mới + unit test + Swagger | F104: Tuấn | G104: API | H104: 0.25 | M104: =SUM(H104:L104) | N104: 46344 | O104: 46344 | P104: =NETWORKDAYS(N104,O104) | Q104: 1.1 | R104: Đúng dữ liệu, phân trang, phân quyền đối tác | S104: 46346 | T104: Chưa bắt đầu | U104: Phát triển API
A105: API-072 | B105: P3 Nhóm B – Giá, VAT, hợp đồng, tín dụng, free-bag (hạn 20/11) | C105: ZRDM-005 | D105: GET /api/fi/tax-codes – Mã thuế GTGT: Lấy danh mục mã thuế & thuế suất | E105: Code mới + unit test + Swagger | F105: Tuấn | G105: API | H105: 0.25 | M105: =SUM(H105:L105) | N105: 46344 | O105: 46344 | P105: =NETWORKDAYS(N105,O105) | Q105: 1.1 | R105: Đúng dữ liệu, phân trang, phân quyền đối tác | S105: 46346 | T105: Chưa bắt đầu | U105: Phát triển API
A106: API-073 | B106: P3 Nhóm B – Giá, VAT, hợp đồng, tín dụng, free-bag (hạn 20/11) | C106: ZRDM-006 | D106: GET /api/sd/contracts – Hợp đồng bán hàng: Lấy danh sách HĐ theo KH/ngày | E106: Code mới + unit test + Swagger | F106: Tuấn | G106: API | H106: 0.25 | M106: =SUM(H106:L106) | N106: 46344 | O106: 46345 | P106: =NETWORKDAYS(N106,O106) | Q106: N.006a | R106: Đúng dữ liệu, phân trang, phân quyền đối tác | S106: 46346 | T106: Chưa bắt đầu | U106: Phát triển API
A107: API-074 | B107: P3 Nhóm B – Giá, VAT, hợp đồng, tín dụng, free-bag (hạn 20/11) | C107: ZRDM-006 | D107: GET /api/sd/contracts/{contractNo} – Hợp đồng bán hàng: Lấy chi tiết 1 HĐ để xuất mẫu biểu | E107: Code mới + unit test + Swagger | F107: Tuấn | G107: API | H107: 0.5 | M107: =SUM(H107:L107) | N107: 46345 | O107: 46345 | P107: =NETWORKDAYS(N107,O107) | Q107: N.006a | R107: Đúng dữ liệu, phân trang, phân quyền đối tác | S107: 46346 | T107: Chưa bắt đầu | U107: Phát triển API
A108: API-075 | B108: P3 Nhóm B – Giá, VAT, hợp đồng, tín dụng, free-bag (hạn 20/11) | C108: ZRDM-006 | D108: POST /api/sd/contracts – Hợp đồng bán hàng: Tạo 1 HĐ | E108: Điều chỉnh + test + Swagger | F108: Tuấn | G108: API | H108: 0.25 | M108: =SUM(H108:L108) | N108: 46345 | O108: 46346 | P108: =NETWORKDAYS(N108,O108) | Q108: N.006b | R108: Có requestId, log 2 phía, mã lỗi đúng | S108: 46346 | T108: Chưa bắt đầu | U108: Phát triển API
A109: B.T | B109: P3 Nhóm B – Giá, VAT, hợp đồng, tín dụng, free-bag (hạn 20/11) | C109: ZRDM-004–009 | D109: Test nhóm B: kịch bản trùng/overlap giá, VAT, HĐ, free-bag – bàn giao nhóm B | E109: Báo cáo test nhóm B | F109: Tuấn | G109: Workshop/Test | H109: 0.5 | I109: 0.25 | L109: 0.5 | M109: =SUM(H109:L109) | N109: 46345 | O109: 46346 | P109: =NETWORKDAYS(N109,O109) | Q109: API nhóm B | R109: 100% test case pass – bàn giao 20/11 | T109: Chưa bắt đầu | U109: Kiểm thử
A110: API-076 | B110: P3 Nhóm B – Giá, VAT, hợp đồng, tín dụng, free-bag (hạn 20/11) | C110: ZRDM-006 | D110: POST /api/sd/contracts/jobs/create – Hợp đồng bán hàng: Tạo nhiều HĐ (job nền) | E110: Code mới + unit test + Swagger | F110: Tuấn | G110: API | H110: 0.5 | M110: =SUM(H110:L110) | N110: 46346 | O110: 46346 | P110: =NETWORKDAYS(N110,O110) | Q110: N.006b | R110: Có requestId, log 2 phía, mã lỗi đúng | S110: 46346 | T110: Chưa bắt đầu | U110: Phát triển API
A111: API-084 | B111: P3 Nhóm B – Giá, VAT, hợp đồng, tín dụng, free-bag (hạn 20/11) | C111: ZRDM-009 | D111: POST /api/sd/freebag-programs/invalidate – Chương trình free-bag: Hủy hiệu lực chương trình | E111: Code mới + unit test + Swagger | F111: Tuấn | G111: API | H111: 0.25 | M111: =SUM(H111:L111) | N111: 46346 | O111: 46347 | P111: =NETWORKDAYS(N111,O111) | Q111: N.009 | R111: Có requestId, log 2 phía, mã lỗi đúng | S111: 46346 | T111: Chưa bắt đầu | U111: Phát triển API
A112: API-085 | B112: P3 Nhóm B – Giá, VAT, hợp đồng, tín dụng, free-bag (hạn 20/11) | C112: ZRDM-009 | D112: GET /api/sd/freebag-programs – Chương trình free-bag: Lấy danh sách / chi tiết chương trình | E112: Code mới + unit test + Swagger | F112: Tuấn | G112: API | H112: 0.25 | M112: =SUM(H112:L112) | N112: 46347 | O112: 46347 | P112: =NETWORKDAYS(N112,O112) | Q112: N.009b | R112: Đúng dữ liệu, phân trang, phân quyền đối tác | S112: 46346 | T112: Chưa bắt đầu | U112: Phát triển API
A113: C.S | B113: P4 Nhóm C – HĐ free-bag, sản lượng, credit memo, FI chiết khấu (hạn 27/11) | C113: ZRDM-010/011/012 | D113: Spec chi tiết HĐ free-bag, định nghĩa sản lượng tính CK, credit memo request + test case | E113: Spec SD nhóm C + test case | F113: Hằng | G113: Workshop/Test | L113: 0.75 | M113: =SUM(H113:L113) | N113: 46332 | O113: 46337 | P113: =NETWORKDAYS(N113,O113) | Q113: B.S2 | R113: Spec được Tafico duyệt | T113: Chưa bắt đầu | U113: Phân tích & spec
A114: N.013 | B114: P4 Nhóm C – HĐ free-bag, sản lượng, credit memo, FI chiết khấu (hạn 27/11) | C114: ZRDM-013/016/019/020 | D114: Khung FI chung Z_RDM_FI_POST (copy Z_EFI011): CK trực tiếp, CK TT trước, lãi quá hạn, accrual; nhánh quyết toán âm; đánh dấu chứng từ RDM (ZRDM_FI_DOC) | E114: FM RFC + bảng ZRDM_FI_DOC | F114: Nam | G114: ABAP | I114: 2 | M114: =SUM(H114:L114) | N114: 46340 | O114: 46347 | P114: =NETWORKDAYS(N114,O114) | Q114: D.S2 | R114: Định khoản đúng ma trận FI | S114: 46353 | T114: Chưa bắt đầu | U114: Phát triển ABAP
A115: N.010 | B115: P4 Nhóm C – HĐ free-bag, sản lượng, credit memo, FI chiết khấu (hạn 27/11) | C115: ZRDM-010 | D115: Z_RDM_FREEBAG_CONTRACT: tạo + nhánh cập nhật HĐ free-bag (tách từ hàm RDM 2022) | E115: FM RFC | F115: Nam | G115: ABAP | I115: 1.5 | M115: =SUM(H115:L115) | N115: 46345 | O115: 46349 | P115: =NETWORKDAYS(N115,O115) | Q115: C.S | R115: Tạo & sửa thành công | S115: 46353 | T115: Chưa bắt đầu | U115: Phát triển ABAP
A116: API-086 | B116: P4 Nhóm C – HĐ free-bag, sản lượng, credit memo, FI chiết khấu (hạn 27/11) | C116: ZRDM-010 | D116: POST /api/sd/freebag-contracts – HĐ free-bag: Tạo HĐ free-bag | E116: Code mới + unit test + Swagger | F116: Tuấn | G116: API | H116: 0.5 | M116: =SUM(H116:L116) | N116: 46349 | O116: 46349 | P116: =NETWORKDAYS(N116,O116) | Q116: N.010 | R116: Có requestId, log 2 phía, mã lỗi đúng | S116: 46353 | T116: Chưa bắt đầu | U116: Phát triển API
A117: API-087 | B117: P4 Nhóm C – HĐ free-bag, sản lượng, credit memo, FI chiết khấu (hạn 27/11) | C117: ZRDM-010 | D117: POST /api/sd/freebag-contracts/change – HĐ free-bag: Cập nhật HĐ free-bag (khi tồn thay đổi) | E117: Code mới + unit test + Swagger | F117: Tuấn | G117: API | H117: 0.25 | M117: =SUM(H117:L117) | N117: 46349 | O117: 46349 | P117: =NETWORKDAYS(N117,O117) | Q117: N.010 | R117: Có requestId, log 2 phía, mã lỗi đúng | S117: 46353 | T117: Chưa bắt đầu | U117: Phát triển API
A118: API-088 | B118: P4 Nhóm C – HĐ free-bag, sản lượng, credit memo, FI chiết khấu (hạn 27/11) | C118: ZRDM-010 | D118: GET /api/sd/freebag-contracts/{contractNo} – HĐ free-bag: Lấy chi tiết HĐ free-bag | E118: Code mới + unit test + Swagger | F118: Tuấn | G118: API | H118: 0.25 | M118: =SUM(H118:L118) | N118: 46349 | O118: 46349 | P118: =NETWORKDAYS(N118,O118) | Q118: N.006a | R118: Đúng dữ liệu, phân trang, phân quyền đối tác | S118: 46353 | T118: Chưa bắt đầu | U118: Phát triển API
A119: N.011a | B119: P4 Nhóm C – HĐ free-bag, sản lượng, credit memo, FI chiết khấu (hạn 27/11) | C119: ZRDM-011 | D119: RFC Z_RDM_SALES_VOLUME_GET: sản lượng tính CK (VBRK/VBRP/LIPS), phân trang khối lượng lớn | E119: FM RFC | F119: Nam | G119: ABAP | I119: 1.5 | M119: =SUM(H119:L119) | N119: 46349 | O119: 46350 | P119: =NETWORKDAYS(N119,O119) | Q119: C.S | R119: 1 năm dữ liệu < 60s/trang | S119: 46353 | T119: Chưa bắt đầu | U119: Phát triển ABAP
A120: API-089 | B120: P4 Nhóm C – HĐ free-bag, sản lượng, credit memo, FI chiết khấu (hạn 27/11) | C120: ZRDM-011 | D120: GET /api/sd/sales-volumes – Sản lượng tính chiết khấu: Lấy sản lượng (phân trang, theo KH/kỳ) | E120: Code mới + unit test + Swagger | F120: Tuấn | G120: API | H120: 0.5 | M120: =SUM(H120:L120) | N120: 46350 | O120: 46350 | P120: =NETWORKDAYS(N120,O120) | Q120: N.011a | R120: Đúng dữ liệu, phân trang, phân quyền đối tác | S120: 46353 | T120: Chưa bắt đầu | U120: Phát triển API
A121: API-090 | B121: P4 Nhóm C – HĐ free-bag, sản lượng, credit memo, FI chiết khấu (hạn 27/11) | C121: ZRDM-011 | D121: POST /api/sd/sales-volumes/jobs/export – Sản lượng tính chiết khấu: Trích xuất khối lượng lớn (job nền) | E121: Code mới + unit test + Swagger | F121: Tuấn | G121: API | H121: 0.25 | M121: =SUM(H121:L121) | N121: 46350 | O121: 46350 | P121: =NETWORKDAYS(N121,O121) | Q121: N.011a | R121: Có requestId, log 2 phía, mã lỗi đúng | S121: 46353 | T121: Chưa bắt đầu | U121: Phát triển API
...

Sheet Gantt
A1: GANTT – 29/10/2026 → 07/12/2026
A2: Màu theo người chủ trì: Tuấn xanh dương · Nam xanh lá · Khang vàng · Sơn đỏ · Hằng tím. Cột xám = thứ Bảy (OT). Ngày lấy từ sheet WBS (sửa WBS → Gantt tự đổi)
F3: T5 | G3: T6 | H3: T7 | I3: T2 | J3: T3 | K3: T4 | L3: T5 | M3: T6 | N3: T7 | O3: T2 | P3: T3 | Q3: T4 | R3: T5 | S3: T6 | T3: T7 | U3: T2 | V3: T3 | W3: T4 | X3: T5 | Y3: T6 | Z3: T7 | AA3: T2 | AB3: T3 | AC3: T4 | AD3: T5 | AE3: T6 | AF3: T7 | AG3: T2 | AH3: T3 | AI3: T4 | AJ3: T5 | AK3: T6 | AL3: T7 | AM3: T2
A4: Mã | B4: Công việc | C4: Chủ trì | D4: Bắt đầu | E4: Kết thúc | F4: 46324 | G4: 46325 | H4: 46326 | I4: 46328 | J4: 46329 | K4: 46330 | L4: 46331 | M4: 46332 | N4: 46333 | O4: 46335 | P4: 46336 | Q4: 46337 | R4: 46338 | S4: 46339 | T4: 46340 | U4: 46342 | V4: 46343 | W4: 46344 | X4: 46345 | Y4: 46346 | Z4: 46347 | AA4: 46349 | AB4: 46350 | AC4: 46351 | AD4: 46352 | AE4: 46353 | AF4: 46354 | AG4: 46356 | AH4: 46357 | AI4: 46358 | AJ4: 46359 | AK4: 46360 | AL4: 46361 | AM4: 46363
A5: ='WBS chi tiết'!A5 | B5: Kickoff: chốt phạm vi 24 đối tượng, kế hoạch 40 ngày, quy trình duyệt spec & change reques | C5: ='WBS chi tiết'!F5 | D5: ='WBS chi tiết'!N5 | E5: ='WBS chi tiết'!O5
A6: ='WBS chi tiết'!A6 | B6: Kiểm tra môi trường: user RFC DEV930 (S_RFC, S_TCODE), NCo 3.1, SQL Server, server API, qu | C6: ='WBS chi tiết'!F6 | D6: ='WBS chi tiết'!N6 | E6: ='WBS chi tiết'!O6
A7: ='WBS chi tiết'!A7 | B7: Workshop SD: chốt open point (loại xe = CG3?, chiều VAT, logic "theo xe", định nghĩa sản l | C7: ='WBS chi tiết'!F7 | D7: ='WBS chi tiết'!N7 | E7: ='WBS chi tiết'!O7
A8: ='WBS chi tiết'!A8 | B8: Workshop FI: ma trận bút toán (doc type, posting key, tài khoản, đối tượng CO), quyết toán | C8: ='WBS chi tiết'!F8 | D8: ='WBS chi tiết'!N8 | E8: ='WBS chi tiết'!O8
A9: ='WBS chi tiết'!A9 | B9: Mapping field từng API (input/output), bảng mã lỗi nghiệp vụ, sign-off BRD | C9: ='WBS chi tiết'!F9 | D9: ='WBS chi tiết'!N9 | E9: ='WBS chi tiết'!O9
A10: ='WBS chi tiết'!A10 | B10: GET /api/auth/users – Danh sách user | C10: ='WBS chi tiết'!F10 | D10: ='WBS chi tiết'!N10 | E10: ='WBS chi tiết'!O10
A11: ='WBS chi tiết'!A11 | B11: GET /api/postings/{id} – Tra cứu theo Id | C11: ='WBS chi tiết'!F11 | D11: ='WBS chi tiết'!N11 | E11: ='WBS chi tiết'!O11
A12: ='WBS chi tiết'!A12 | B12: GET /api/postings/{operation}/{requestId} – Tra cứu theo requestId | C12: ='WBS chi tiết'!F12 | D12: ='WBS chi tiết'!N12 | E12: ='WBS chi tiết'!O12
A13: ='WBS chi tiết'!A13 | B13: GET /api/postings – Tìm kiếm danh sách | C13: ='WBS chi tiết'!F13 | D13: ='WBS chi tiết'!N13 | E13: ='WBS chi tiết'!O13
A14: ='WBS chi tiết'!A14 | B14: GET /api/sap/ping – Kiểm tra kết nối | C14: ='WBS chi tiết'!F14 | D14: ='WBS chi tiết'!N14 | E14: ='WBS chi tiết'!O14
A15: ='WBS chi tiết'!A15 | B15: Chuẩn ABAP: template FM RFC (RETURN, COMMIT/ROLLBACK, gọi log), quy ước đặt tên, code revi | C15: ='WBS chi tiết'!F15 | D15: ='WBS chi tiết'!N15 | E15: ='WBS chi tiết'!O15
A16: ='WBS chi tiết'!A16 | B16: Thiết kế kiến trúc: chuẩn REST (resource/hành động, paging, ProblemDetails), bảng mã lỗi, | C16: ='WBS chi tiết'!F16 | D16: ='WBS chi tiết'!N16 | E16: ='WBS chi tiết'!O16
... A166: ='WBS chi tiết'!A166 | B166: Go-live, hypercare, bàn giao source code & tài liệu, nghiệm thu | C166: ='WBS chi tiết'!F166 | D166: ='WBS chi tiết'!N166 | E166: ='WBS chi tiết'!O166

Sheet Nguồn lực theo tuần
A1: PHÂN BỔ NGUỒN LỰC THEO TUẦN (ngày công)
A2: Năng lực chuẩn = số ngày T2–T6 trong tuần; phần vượt = làm thêm thứ Bảy. Số liệu tính từ lịch xếp tự động (v1.0)
A4: Thành viên | B4: Tuần 1 29/10–31/10 | C4: Tuần 2 02/11–07/11 | D4: Tuần 3 09/11–14/11 | E4: Tuần 4 16/11–21/11 | F4: Tuần 5 23/11–28/11 | G4: Tuần 6 30/11–05/12 | H4: Tuần 7 07/12–07/12 | I4: Tổng
A5: Năng lực chuẩn (ngày) | B5: 2 | C5: 5 | D5: 5 | E5: 5 | F5: 5 | G5: 5 | H5: 1 | I5: 28
A6: Tuấn | B6: 2.4 | C6: 5 | D6: 6 | E6: 6 | F6: 5.45 | G6: 5.08 | H6: 0.42 | I6: =SUM(B6:H6)
A7: Nam | B7: 1.5 | C7: 5 | D7: 6 | E7: 6 | F7: 5.05 | G7: 4.58 | H7: 0.42 | I7: =SUM(B7:H7)
A8: Khang | B8: 0.38 | C8: 1.5 | D8: 4.13 | E8: 4.5 | F8: 3.56 | G8: 0.94 | H8: 0.25 | I8: =SUM(B8:H8)
A9: Sơn | B9: 0.75 | C9: 2 | D9: 1 | E9: 0 | F9: 0.81 | G9: 1.44 | H9: 0.25 | I9: =SUM(B9:H9)
A10: Hằng | B10: 0.75 | C10: 2.8 | D10: 0.7 | E10: 0.5 | F10: 0.25 | G10: 1.25 | H10: 0.25 | I10: =SUM(B10:H10)
B12: Vượt năng lực chuẩn – có OT thứ Bảy
B13: Tải 80–100%
B14: Tải 30–80% (tư vấn bán thời gian)

Sheet RACI theo SOW
A1: MA TRẬN RACI THEO 24 ĐỐI TƯỢNG SOW
A2: R = thực hiện · A = chịu trách nhiệm cuối · C = tư vấn/duyệt spec · I = được thông báo
A4: Mã SOW | B4: Nghiệp vụ | C4: Loại | D4: Số API | E4: Tuấn | F4: Nam | G4: Khang | H4: Sơn | I4: Hằng | J4: Ghi chú
A5: ZRDM-001 | B5: Danh mục KH & cơ cấu bán hàng | C5: API | D5: =COUNTIF('Danh mục API'!C:C,A5) | E5: A,R | F5: R | H5: I | I5: C | J5: Delta Sold-to/Ship-to cần RFC Z
A6: ZRDM-002 | B6: Danh mục vật tư | C6: API | D6: =COUNTIF('Danh mục API'!C:C,A6) | E6: A,R | F6: I | I6: C
A7: ZRDM-003 | B7: Danh mục TK kế toán & cost center | C7: API | D7: =COUNTIF('Danh mục API'!C:C,A7) | E7: A,R | F7: I | H7: C | J7: COA 1000, CO area G100
A8: ZRDM-004 | B8: Điều kiện giá (niêm yết, sàn, nội bộ) | C8: API | D8: =COUNTIF('Danh mục API'!C:C,A8) | E8: R | F8: A,R | I8: C | J8: Kiểm tra trùng/overlap
A9: ZRDM-005 | B9: Thuế suất GTGT | C9: API | D9: =COUNTIF('Danh mục API'!C:C,A9) | E9: A,R | F9: R | H9: C | I9: C | J9: Chốt chiều ghi thuế
A10: ZRDM-006 | B10: Hợp đồng bán hàng | C10: API | D10: =COUNTIF('Danh mục API'!C:C,A10) | E10: R | F10: A,R | I10: C
A11: ZRDM-007 | B11: Hạn mức tín dụng | C11: API | D11: =COUNTIF('Danh mục API'!C:C,A11) | E11: A,R | F11: I | H11: C | I11: C | J11: Classic/FSCM
A12: ZRDM-008 | B12: Bảo lãnh ngân hàng | C12: – | D12: =COUNTIF('Danh mục API'!C:C,A12) | E12: A | H12: I | I12: I | J12: Không dùng (SOW v1.1)
A13: ZRDM-009 | B13: Chương trình free-bag | C13: API | D13: =COUNTIF('Danh mục API'!C:C,A13) | E13: R | F13: A,R | I13: C | J13: Logic "theo xe"
A14: ZRDM-010 | B14: Sale contract free-bag | C14: API | D14: =COUNTIF('Danh mục API'!C:C,A14) | E14: R | F14: A,R | I14: C | J14: Nhánh cập nhật
A15: ZRDM-011 | B15: Sản lượng tính CK & free-bag đã chi trả | C15: API | D15: =COUNTIF('Danh mục API'!C:C,A15) | E15: R | F15: A,R | H15: I | I15: C | J15: Phân trang khối lượng lớn
A16: ZRDM-012 | B16: Credit memo request | C16: API | D16: =COUNTIF('Danh mục API'!C:C,A16) | E16: R | F16: A,R | H16: C | I16: C | J16: 3 bước 1 lần gọi
A17: ZRDM-013 | B17: Bút toán CK trực tiếp / FI | C17: API | D17: =COUNTIF('Danh mục API'!C:C,A17) | E17: A,R | F17: R | H17: C | I17: I | J17: Quyết toán âm
A18: ZRDM-014 | B18: Z-Report CK thanh toán trước | C18: Z-Report | D18: =COUNTIF('Danh mục API'!C:C,A18) | E18: I | F18: A | G18: R | H18: C
A19: ZRDM-015 | B19: API lấy CK thanh toán trước | C19: API | D19: =COUNTIF('Danh mục API'!C:C,A19) | E19: R | F19: A | G19: R | H19: C | J19: RFC do Khang
A20: ZRDM-016 | B20: Hạch toán CK thanh toán trước | C20: API | D20: =COUNTIF('Danh mục API'!C:C,A20) | E20: C | F20: A,R | H20: C | J20: Khung FI chung
A21: ZRDM-017 | B21: Z-Report lãi quá hạn | C21: Z-Report | D21: =COUNTIF('Danh mục API'!C:C,A21) | E21: I | F21: A | G21: R | H21: C | J21: Trường GAP
A22: ZRDM-018 | B22: API lấy lãi quá hạn | C22: API | D22: =COUNTIF('Danh mục API'!C:C,A22) | E22: R | F22: A | G22: R | H22: C | J22: RFC do Khang
A23: ZRDM-019 | B23: Hạch toán lãi quá hạn | C23: API | D23: =COUNTIF('Danh mục API'!C:C,A23) | E23: C | F23: A,R | H23: C
A24: ZRDM-020 | B24: Hạch toán trích trước (accrual) | C24: API | D24: =COUNTIF('Danh mục API'!C:C,A24) | E24: C | F24: A,R | H24: C
A25: ZRDM-021 | B25: Hoàn nhập accrual khi sai | C25: API | D25: =COUNTIF('Danh mục API'!C:C,A25) | E25: A,R | F25: R | H25: C | J25: Chỉ chứng từ qua RDM
A26: ZRDM-022 | B26: Tự động hoàn nhập đầu kỳ | C26: API | D26: =COUNTIF('Danh mục API'!C:C,A26) | E26: A,R | F26: R | H26: C | J26: Job Hangfire
A27: ZRDM-023 | B27: Z-Report biên bản đối chiếu công nợ | C27: Z-Report | D27: =COUNTIF('Danh mục API'!C:C,A27) | E27: I | F27: A | G27: R | H27: C | J27: Layout Fico-YTL
A28: ZRDM-024 | B28: API data biên bản đối chiếu | C28: API | D28: =COUNTIF('Danh mục API'!C:C,A28) | E28: A,R | F28: R | H28: C | J28: Ký số/Websale ngoài phạm vi

Sheet Kế hoạch test
A1: KẾ HOẠCH KIỂM THỬ
A2: Mỗi API tối thiểu: 1 case đúng, 1 case lỗi nghiệp vụ, 1 case phân quyền (401/403); API ghi thêm 1 case gửi trùng requestId
A4: Cấp độ test | B4: Phạm vi | C4: Công cụ / môi trường | D4: Người làm | E4: Người duyệt | F4: Thời gian | G4: Tiêu chí đạt | H4: Số case (ước)
A5: Unit test .NET | B5: Tầng Application/Sap: validate, mapping, idempotency, chuyển mã lỗi | C5: xUnit + FluentAssertions, CI build | D5: Tuấn, Nam | E5: Nam | F5: Liên tục, chốt 25–28/11 | G5: 100% pass, coverage ≥ 70% Application | H5: 250
A6: Unit test ABAP | B6: FM RFC, khung FI, kiểm tra overlap giá, logging SAP | C6: ABAP Unit / SE37 test data, DEV930 | D6: Nam, Khang | E6: Nam | F6: Theo từng object | G6: Pass trên test data chuẩn | H6: 60
A7: Integration (API ↔ SAP DEV930) | B7: Từng API gọi thật SAP DEV930 | C7: Swagger internal, Postman collection | D7: Tuấn | E7: Nam | F7: Cuối mỗi nhóm A/B/C/D | G7: Đúng dữ liệu, chứng từ đúng định khoản | H7: 394
A8: Test nghiệp vụ nhóm (A/B/C/D) | B8: Kịch bản theo spec của Hằng/Sơn | C8: DEV930 + đối soát FB03/VA03/VK13/FBL5N | D8: Tuấn, Nam, Khang | E8: Hằng (SD), Sơn (FI) | F8: 13/11, 20/11, 27/11, 30/11 | G8: 100% case pass trước bàn giao | H8: 120
A9: Test 3 báo cáo Z | B9: EPD, lãi quá hạn, đối chiếu công nợ | C9: So khớp tính tay của kế toán, FBL5N/FD10N | D9: Khang | E9: Sơn | F9: 25–30/11 | G9: Kế toán xác nhận số liệu | H9: 30
A10: Test bảo mật | B10: JWT (sai chữ ký, hết hạn, refresh), role, phạm vi dữ liệu theo đối tác, Swagger internal chỉ localhost | C10: Postman, script tự động | D10: Tuấn | E10: Nam | F10: 28/11–01/12 | G10: Không truy cập chéo dữ liệu; 401/403 đúng | H10: 40
A11: Test logging 2 phía | B11: Correlation-Id API → SAP; SapCallLog ↔ ZRDM_API_LOG ↔ SLG1 | C11: ZRDM_LOG_VIEW, /api/admin/sap-logs | D11: Tuấn, Nam | E11: Nam | F11: Trong SIT | G11: 100% lời gọi ghi được log 2 phía | H11: 20
A12: Test chống trùng / lỗi kết nối | B12: Gửi trùng requestId, ngắt SAP giữa chừng (Unknown), timeout | C12: Script + tắt RFC destination | D12: Tuấn | E12: Nam | F12: Trong SIT | G12: Không sinh chứng từ trùng | H12: 15
A13: Test hiệu năng | B13: Sync master data, sản lượng (011), đối chiếu công nợ (024) | C13: k6 / script, dữ liệu 1 năm | D13: Nam | E13: Tuấn | F13: 01–02/12 | G13: Ngưỡng thời gian đã chốt | H13: 10
A14: SIT end-to-end | B14: RDM ↔ API ↔ SAP theo quy trình nghiệp vụ | C14: Môi trường QAS/DEV930 | D14: Tuấn, Nam + RDM | E14: Sơn, Hằng | F14: 01–02/12 | G14: Không lỗi Critical/High | H14: 60
A15: UAT | B15: Người dùng Tafico | C15: QAS | D15: Tafico | E15: Sơn, Hằng | F15: 03–04/12 | G15: Biên bản UAT ký | H15: 50

Sheet Logging & Bảo mật
A1: THIẾT KẾ REST / JWT / LOGGING (API + SAP)
A4: Hạng mục | B4: Thành phần | C4: Thiết kế | D4: Người làm | E4: Mã WBS
A5: REST | B5: Chuẩn endpoint | C5: Mỗi đối tượng × hành động 1 endpoint; GET đọc, POST ghi/hành động; phân trang page/pageSize; lỗi theo ProblemDetails + mã lỗi nghiệp vụ | D5: Tuấn | E5: 1.1
A6: REST | B6: Mã HTTP | C6: 200 thành công · 400 dữ liệu sai · 401/403 xác thực/quyền · 409 trùng requestId khác nội dung · 422 lỗi nghiệp vụ SAP · 502 không rõ kết quả · 503 SAP không sẵn sàng | D6: Tuấn | E6: 1.1
A7: REST | B7: Idempotency | C7: API ghi bắt buộc requestId; (Operation, RequestId) duy nhất + hash payload; không retry lệnh ghi SAP | D7: Tuấn | E7: 1.1
A8: JWT | B8: Xác thực | C8: POST /api/auth/token, /api/auth/refresh; HS256/RS256, hết hạn 60 phút, refresh 8h; xoay khóa ký | D8: Tuấn | E8: 1.2
A9: JWT | B9: Phân quyền | C9: Role Admin / Partner(đọc) / Partner(ghi); claim phạm vi (sales org, sold-to) – lọc dữ liệu, ngoài phạm vi → 403 (sửa lỗi KH thấy full data) | D9: Tuấn | E9: 1.2
A10: Logging API | B10: Serilog | C10: Console + file rolling + SQL; Correlation-Id từ header X-Correlation-Id hoặc tự sinh; che mật khẩu/token | D10: Tuấn | E10: 1.3
A11: Logging API | B11: rdm.SapCallLog | C11: Mỗi lời gọi SAP: hàm, thời gian, kết quả, thông điệp RETURN, Correlation-Id; API /api/admin/sap-calls | D11: Tuấn | E11: 1.3
A12: Logging SAP | B12: Bảng ZRDM_API_LOG | C12: Header: LOGID, CORR_ID, SOW_ID, FUNCNAME, RDM_USER, REQUEST_ID, START/END, STATUS, DOC_NO, DURATION | D12: Nam | E12: L.1
A13: Logging SAP | B13: Bảng ZRDM_API_LOGI | C13: Chi tiết: LOGID, SEQ, MSGTY, MSGID, MSGNO, MESSAGE, payload rút gọn | D13: Nam | E13: L.1
A14: Logging SAP | B14: Application Log (SLG1) | C14: Object ZRDM, subobject theo SOW (PRICE, CONTRACT, FREEBAG, FIPOST, REPORT…); BAL_LOG_CREATE / BAL_DB_SAVE | D14: Nam | E14: L.1
A15: Logging SAP | B15: FM Z_RDM_LOG_WRITE | C15: Gọi ở đầu/cuối mọi FM RDM; ghi cả khi lỗi (commit riêng, không bị rollback cùng nghiệp vụ) | D15: Nam | E15: L.1
... A18: Logging SAP | B18: Gắn log FM có sẵn | C18: Z_EFI011, Z_EFI009, Z_ESD012/013/014/015/016 + 3 báo cáo Z | D18: Nam, Khang | E18: L.4

Sheet Tài liệu bàn giao
A1: DANH MỤC TÀI LIỆU BÀN GIAO
A4: STT | B4: Tài liệu | C4: Nội dung | D4: Người viết | E4: Người duyệt | F4: Hạn | G4: Mã WBS
A5: 1 | B5: Decision log SD + FI | C5: Các quyết định open point, người chốt, ngày chốt | D5: Hằng, Sơn | E5: Tafico | F5: 04/11/2026 | G5: 0.3, 0.4
A6: 2 | B6: Ma trận bút toán FI | C6: Doc type, posting key, tài khoản, đối tượng CO cho 013/016/019/020/021/022 | D6: Sơn | E6: KT trưởng Tafico | F6: 04/11/2026 | G6: 0.4
A7: 3 | B7: BRD + mapping field | C7: Input/output từng API, mã lỗi nghiệp vụ | D7: Tuấn | E7: RDM, Tafico | F7: 05/11/2026 | G7: 0.5
A8: 4 | B8: Spec giá & khuyến mại | C8: ZVLP/ZVDI/ZMIN/ZVIV, free-bag, HĐ, sản lượng, credit memo + test case | D8: Hằng | E8: Tafico | F8: 10/11/2026 | G8: B.S, B.S2, C.S
A9: 5 | B9: FS 3 báo cáo Z + spec FI | C9: Logic, công thức, layout, test case hạch toán | D9: Sơn | E9: Tafico | F9: 11/11/2026 | G9: D.S, D.S2
A10: 6 | B10: Tài liệu kiến trúc (SAD) | C10: REST, JWT, logging 2 phía, idempotency, triển khai | D10: Tuấn | E10: Nam | F10: 04/11/2026 | G10: 1.1
A11: 7 | B11: API Integration Guide + OpenAPI | C11: 112 API: request/response mẫu, mã lỗi, luồng gọi | D11: Tuấn | E11: Nam, RDM | F11: 02/12/2026 | G11: 7.1
A12: 8 | B12: TS ABAP | C12: Toàn bộ FM RFC, bảng Z, logging SAP | D12: Nam | E12: Nam | F12: 03/12/2026 | G12: 7.2
A13: 9 | B13: TS 3 báo cáo Z | C13: Thiết kế kỹ thuật report + bảng kết quả | D13: Khang | E13: Nam | F13: 03/12/2026 | G13: 7.2K
A14: 10 | B14: Báo cáo test (unit, nhóm, bảo mật, hiệu năng) | C14: Kết quả, lỗi, coverage | D14: Tuấn, Nam, Khang | E14: Nam | F14: 02/12/2026 | G14: 6.x
A15: 11 | B15: Biên bản SIT / UAT | C15: Kịch bản, kết quả, chữ ký | D15: Tuấn | E15: Tafico | F15: 04/12/2026 | G15: 6.2, 6.4
A16: 12 | B16: User guide | C16: Báo cáo Z, bút toán FI, luồng giá/khuyến mại | D16: Sơn, Hằng, Khang | E16: Tafico | F16: 04/12/2026 | G16: 7.4
... A18: 14 | B18: Checklist go-live + biên bản bàn giao | C18: Transport, cấu hình PRD, smoke test | D18: Nam, Tuấn | E18: Tafico | F18: 07/12/2026 | G18: 7.5, 7.6

Sheet Rủi ro & Open point
A1: RỦI RO & OPEN POINT CẦN CHỐT
A4: STT | B4: Mã SOW | C4: Nội dung | D4: Ảnh hưởng | E4: Mức | F4: Người xử lý | G4: Hạn chốt | H4: Hướng xử lý
A5: 1 | B5: ZRDM-001 | C5: Loại xe có đúng = nhóm khách hàng 3 không | D5: Sai danh mục loại xe | E5: TB | F5: Hằng | G5: 04/11 | H5: Chốt trong workshop SD
A6: 2 | B6: ZRDM-003 | C6: Đối soát toàn bộ để bắt khóa/xóa TK, cost center | D6: RDM dùng TK đã khóa | E6: TB | F6: Sơn | G6: 04/11 | H6: Sync full + so sánh cờ khóa
A7: 3 | B7: ZRDM-004 | C7: Phạm vi lớn nhất, 6 luồng giá; overlap hiệu lực | D7: Trễ nhóm B, sai giá | E7: Cao | F7: Nam, Hằng | G7: 06/11 | H7: Spec sớm, test case overlap riêng
A8: 4 | B8: ZRDM-005 | C8: RDM ghi thuế lên SAP hay SAP cấp thuế cho RDM | D8: Làm sai chiều API | E8: TB | F8: Hằng, Sơn | G8: 04/11 | H8: Chốt chiều; đã chuẩn bị cả GET và POST
A9: 5 | B9: ZRDM-006 | C9: Mã dịch vụ tạo HĐ hàng loạt | D9: Không tạo được HĐ | E9: TB | F9: Hằng | G9: 04/11
A10: 6 | B10: ZRDM-007 | C10: Credit Classic hay FSCM | D10: Sai nguồn dữ liệu | E10: TB | F10: Sơn | G10: 04/11 | H10: Hiện đọc KNKK (Classic)
A11: 7 | B11: ZRDM-009 | C11: Logic "theo xe" của free-bag | D11: Trễ nhóm B | E11: Cao | F11: Hằng | G11: 04/11 | H11: Chốt ví dụ số liệu cụ thể
A12: 8 | B12: ZRDM-011 | C12: Định nghĩa "sản lượng"; khối lượng dữ liệu lớn | D12: Sai CK, timeout | E12: Cao | F12: Hằng, Nam | G12: 06/11 | H12: Phân trang, job nền, test hiệu năng
A13: 9 | B13: ZRDM-012 | C13: 3 bước phải chạy trọn trong 1 lần gọi | D13: Chứng từ dở dang | E13: Cao | F13: Nam | G13: – | H13: 1 LUW, rollback toàn bộ
A14: 10 | B14: ZRDM-013 | C14: Chưa có trong file mapping POST; nhánh quyết toán âm | D14: Định khoản sai | E14: Cao | F14: Sơn | G14: 04/11 | H14: Ma trận bút toán ký duyệt
A15: 11 | B15: ZRDM-014 | C15: Quy tắc % chiết khấu theo ngày thanh toán | D15: Sai số liệu báo cáo | E15: Cao | F15: Sơn | G15: 05/11
A16: 12 | B16: ZRDM-017 | C16: Định nghĩa trường điều chỉnh (GAP) | D16: Sai lãi | E16: Cao | F16: Sơn | G16: 05/11
A17: 13 | B17: ZRDM-022 | C17: Áp dụng hoàn nhập tự động cho free-bag? | D17: Thiếu/thừa bút toán | E17: TB | F17: Sơn | G17: 04/11
A18: 14 | B18: Chung | C18: Nguồn lực Tuấn & Nam ~100% + OT thứ Bảy; 5 API nhóm B/D xong sau hạn SOW 1 ngày | D18: Trễ bàn giao | E18: Cao | F18: Tuấn | G18: – | H18: Ưu tiên theo hạn, chốt dời 1 ngày hoặc tăng OT; không thêm scope
A19: 15 | B19: Chung | C19: Open point chốt muộn sau 04/11 | D19: Đẩy lùi toàn bộ lịch | E19: Cao | F19: Tuấn | G19: 04/11 | H19: Escalate PM Tafico ngày 05/11
A20: 16 | B20: Chung | C20: User RFC/quyền transport QAS/PRD chưa sẵn sàng | D20: Trễ go-live | E20: TB | F20: Nam | G20: 25/11 | H20: Yêu cầu Basis sớm
A21: 17 | B21: Chung | C21: Lỗ hổng phân quyền dữ liệu (KH thấy full data) | D21: Lộ dữ liệu | E21: Cao | F21: Tuấn | G21: 06/11 | H21: WBS 1.2 – scope theo đối tác + test bảo mật

Sheet Chi phí & Đóng góp Tuấn
A1: CHI PHÍ DỰ ÁN & ĐÓNG GÓP CỦA TUẤN
A2: Đơn vị: triệu VNĐ · md = ngày công. Ô nền vàng là số nhập (có thể sửa), các ô khác là công thức lấy từ sheet WBS / Danh mục API
A4: 1. CHI PHÍ PHƯƠNG ÁN ĐỀ XUẤT – Tuấn không tính phí
A5: Thành viên | B5: Vai trò | C5: Công (md) | D5: Ngân sách | E5: Đơn giá suy ra (tr/md) | F5: % công dự án | G5: Ghi chú
A6: Tuấn | B6: SA / ABAP / BA | C6: =SUM('WBS chi tiết'!H5:H166) | D6: 0 | E6: =IF(C6=0,0,D6/C6) | F6: =C6/C$11 | G6: Không tính phí – toàn bộ công của Tuấn là đóng góp cho dự án
A7: Nam | B7: ABAP / Techlead | C7: =SUM('WBS chi tiết'!I5:I166) | D7: 140 | E7: =IF(C7=0,0,D7/C7) | F7: =C7/C$11 | G7: Logging SAP, FM RFC, khung FI, API hạch toán 016/019/020, review, transport
A8: Khang | B8: ABAP | C8: =SUM('WBS chi tiết'!J5:J166) | D8: 30 | E8: =IF(C8=0,0,D8/C8) | F8: =C8/C$11 | G8: 3 báo cáo Z + RFC đọc kết quả 015/018
A9: Hằng | B9: SD consultant | C9: =SUM('WBS chi tiết'!L5:L166) | D9: 15 | E9: =IF(C9=0,0,D9/C9) | F9: =C9/C$11 | G9: Spec giá, khuyến mại, hợp đồng, sản lượng, credit memo
A10: Sơn | B10: FICO consultant | C10: =SUM('WBS chi tiết'!K5:K166) | D10: 10 | E10: =IF(C10=0,0,D10/C10) | F10: =C10/C$11 | G10: Spec 3 báo cáo + ma trận bút toán FI
A11: TỔNG | C11: =SUM(C6:C10) | D11: =SUM(D6:D10) | E11: =D11/SUM(C7:C10) | F11: =C11/C$11 | G11: Đơn giá bình quân của các thành viên có tính phí
A13: 2. ĐÓNG GÓP CỤ THỂ CỦA TUẤN (không tính phí)
A14: Hạng mục | B14: Công Tuấn (md) | C14: % công Tuấn | D14: Số đầu việc | E14: Quy đổi theo đơn giá BQ team | G14: Nội dung cụ thể
A15: Phân tích & spec | B15: =SUMIFS('WBS chi tiết'!H5:H166,'WBS chi tiết'!U5:U166,A15) | C15: =IF($C$6=0,0,B15/$C$6) | D15: =COUNTIFS('WBS chi tiết'!U5:U166,A15,'WBS chi tiết'!H5:H166,">0") | E15: =B15*$E$11 | G15: Workshop SD/FI, mapping field 24 đối tượng, BRD, chốt open point, decision log
A16: Kiến trúc & bảo mật | B16: =SUMIFS('WBS chi tiết'!H5:H166,'WBS chi tiết'!U5:U166,A16) | C16: =IF($C$6=0,0,B16/$C$6) | D16: =COUNTIFS('WBS chi tiết'!U5:U166,A16,'WBS chi tiết'!H5:H166,">0") | E16: =B16*$E$11 | G16: Kiến trúc REST, JWT (token/refresh/role/phạm vi dữ liệu theo đối tác), logging API + Correlation-Id
A17: Phát triển API | B17: =SUMIFS('WBS chi tiết'!H5:H166,'WBS chi tiết'!U5:U166,A17) | C17: =IF($C$6=0,0,B17/$C$6) | D17: =COUNTIFS('WBS chi tiết'!U5:U166,A17,'WBS chi tiết'!H5:H166,">0") | E17: =B17*$E$11 | G17: Code/điều chỉnh/rà soát các API .NET (xem số API bên dưới), unit test, Swagger
A18: Kiểm thử | B18: =SUMIFS('WBS chi tiết'!H5:H166,'WBS chi tiết'!U5:U166,A18) | C18: =IF($C$6=0,0,B18/$C$6) | D18: =COUNTIFS('WBS chi tiết'!U5:U166,A18,'WBS chi tiết'!H5:H166,">0") | E18: =B18*$E$11 | G18: Test nhóm A/B/C, unit test tổng, bảo mật, SIT, UAT
A19: Tài liệu & go-live | B19: =SUMIFS('WBS chi tiết'!H5:H166,'WBS chi tiết'!U5:U166,A19) | C19: =IF($C$6=0,0,B19/$C$6) | D19: =COUNTIFS('WBS chi tiết'!U5:U166,A19,'WBS chi tiết'!H5:H166,">0") | E19: =B19*$E$11 | G19: API Integration Guide, runbook vận hành, deploy PRD, bàn giao
A20: TỔNG CÔNG TUẤN | B20: =SUM(B15:B19) | C20: =SUM(C15:C19) | D20: =SUM(D15:D19) | E20: =SUM(E15:E19) | G20: =IF(ROUND(B20-$C$6,2)=0,"Khớp tổng công Tuấn ở mục 1","LỆCH – kiểm tra cột Hạng mục ở WBS")
A22: Chỉ số | B22: Giá trị | G22: Ý nghĩa
A23: Số API Tuấn phụ trách | B23: =COUNTIF('Danh mục API'!O:O,"Tuấn") | G23: Trên tổng số API của dự án
A24: – trong đó API viết mới | B24: =COUNTIFS('Danh mục API'!O:O,"Tuấn",'Danh mục API'!K:K,"Mới")
A25: – trong đó API điều chỉnh | B25: =COUNTIFS('Danh mục API'!O:O,"Tuấn",'Danh mục API'!K:K,"Điều chỉnh")
A26: – trong đó API có sẵn (rà soát + test) | B26: =COUNTIFS('Danh mục API'!O:O,"Tuấn",'Danh mục API'!K:K,"Có sẵn")
A27: Tổng số API dự án | B27: =COUNTIF('Danh mục API'!B:B,"API-*")
A28: Tỷ trọng công Tuấn / toàn dự án | B28: =$C$6/$C$11 | G28: Gánh phần công này nhưng 0 đồng chi phí
A29: Tỷ trọng chi phí Tuấn / ngân sách | B29: =$D$6/$D$11
A30: Giá trị công Tuấn quy đổi (đơn giá BQ team) | B30: =$C$6*$E$11 | G30: Phần chi phí dự án tiết kiệm được nhờ Tuấn không tính phí
A33: 3. NẾU KHÔNG CÓ TUẤN – phải thuê/giao người khác làm phần việc của Tuấn
A34: Chi phí onboarding người thay thế (% công Tuấn) | B34: 0.15 | G34: Người mới phải nắm codebase hiện có, SAP DEV930, nghiệp vụ Tafico, 24 đối tượng SOW
A35: Ngưỡng so sánh (triệu VNĐ) | B35: 200
A36: Công cần thay thế (md) | B36: =$C$6*(1+$B$34)
A38: Phương án | B38: Đơn giá (tr/md) | C38: Chi phí thay Tuấn | D38: Tổng chi phí dự án | E38: Vượt ngưỡng 200tr | F38: Kết luận | G38: Tác động tiến độ
A39: PA1 – Thuê theo đơn giá THẤP NHẤT trong team | B39: =MIN($E$7:$E$10) | C39: =B39*$B$36 | D39: =$D$11+C39 | E39: =D39-$B$35 | F39: =IF(D39>$B$35,"TRÊN "&FIXED($B$35,0)&" triệu","Dưới ngưỡng") | G39: Phải tuyển + onboarding 3–5 ngày → trễ mốc M1 (04/11) và M2 (06/11)
A40: PA2 – Thuê theo đơn giá BÌNH QUÂN team | B40: =$E$11 | C40: =B40*$B$36 | D40: =$D$11+C40 | E40: =D40-$B$35 | F40: =IF(D40>$B$35,"TRÊN "&FIXED($B$35,0)&" triệu","Dưới ngưỡng") | G40: Như PA1
A41: PA3 – Thuê SA/BA/.NET theo đơn giá techlead (Nam) | B41: =$E$7 | C41: =B41*$B$36 | D41: =$D$11+C41 | E41: =D41-$B$35 | F41: =IF(D41>$B$35,"TRÊN "&FIXED($B$35,0)&" triệu","Dưới ngưỡng") | G41: Như PA1
A42: PA4 – Giao Nam làm thêm phần của Tuấn | B42: =$E$7 | C42: =B42*$B$36 | D42: =$D$11+C42 | E42: =D42-$B$35 | F42: =IF(D42>$B$35,"TRÊN "&FIXED($B$35,0)&" triệu","Dưới ngưỡng") | G42: ="Nam cần "&FIXED($C$7+$B$36,1)&" md trong 34 ngày khả dụng → không khả thi, kéo dài ≈ "&FIXED($C$7+$B$36-34,0)&" ngày làm việc"
A44: Đơn giá hòa vốn để vượt ngưỡng | B44: =($B$35-$D$11)/$B$36 | G44: ="Chỉ cần người thay thế có đơn giá > "&FIXED(B44,2)&" tr/md (thấp hơn mọi đơn giá trong team) là tổng chi phí đã vượt "&FIXED($B$35,0)&" triệu"
A46: 4. GIÁ TRỊ NỀN TẢNG BACKEND ĐÃ CÓ (tái sử dụng – không tính vào chi phí)
A47: Chỉ số | B47: Giá trị | G47: Ghi chú
A48: Số API có sẵn + điều chỉnh | B48: =COUNTIF('Danh mục API'!K:K,"Có sẵn")+COUNTIF('Danh mục API'!K:K,"Điều chỉnh")
A49: Công bình quân 1 API viết mới (md) | B49: =AVERAGEIF('Danh mục API'!K:K,"Mới",'Danh mục API'!P:P) | G49: Theo ước lượng WBS
A50: Công nếu phải viết mới toàn bộ (md) | B50: =B48*B49
A51: Công thực tế trong kế hoạch (md) | B51: =SUMIF('Danh mục API'!K:K,"Có sẵn",'Danh mục API'!P:P)+SUMIF('Danh mục API'!K:K,"Điều chỉnh",'Danh mục API'!P:P)
A52: Công tiết kiệm (md) | B52: =B50-B51 | G52: Chưa tính khung JWT, logging, idempotency, job nền, admin UI đã có
A53: Giá trị tiết kiệm (đơn giá thấp nhất team) | B53: =B52*$B$39 | G53: Cần xác nhận nguồn gốc nền tảng trước khi đưa vào hồ sơ
A55: 5. KẾT LUẬN
A56: ="• Ngân sách đề xuất: "&FIXED($D$11,0)&" triệu (Nam "&FIXED($D$7,0)&" · Khang "&FIXED($D$8,0)&" · Hằng "&FIXED($D$9,0)&" · Sơn "&FIXED($D$10,0)&"), Tuấn 0 đồng."
A57: ="• Tuấn gánh "&FIXED($C$6,1)&" ngày công = "&TEXT($C$6/$C$11,"0%")&" công toàn dự án, phụ trách "&FIXED($B$23,0)&"/"&FIXED($B$27,0)&" API ("&FIXED($B$24,0)&" API viết mới), cùng kiến trúc, JWT, logging, phân tích nghiệp vụ, SIT/UAT và tài liệu."
A58: ="• Nếu không có Tuấn, chi phí tối thiểu (PA1) là "&FIXED($D$39,1)&" triệu, PA2 "&FIXED($D$40,1)&" triệu, PA3 "&FIXED($D$41,1)&" triệu – đều trên "&FIXED($B$35,0)&" triệu."
A59: ="• Mức hòa vốn chỉ "&FIXED($B$44,2)&" tr/md: bất kỳ phương án thay thế nào cũng làm chi phí vượt "&FIXED($B$35,0)&" triệu; PA4 (dồn cho Nam) thì không kịp tiến độ."
